{"book":"2 John","lang":"greek","verses":{"1:1":[{"t":"Ὁ","a":" ","g":"The","l":"ὁ","s":"3588","m":"T-NSM","tr":"Ὁ"},{"t":"πρεσβύτερος","a":" ","g":"elder","l":"πρεσβύτερος","s":"4245","m":"A-NSM-C","tr":"πρεσβύτερος"},{"t":"ἐκλεκτῇ","a":" ","g":"To [the] elect","l":"ἐκλεκτός","s":"1588","m":"A-DSF","tr":"ἐκλεκτῇ"},{"t":"κυρίᾳ","a":" ","g":"lady","l":"κυρία","s":"2959","m":"N-DSF","tr":"κυρίᾳ"},{"t":"καὶ","a":" ","g":"and","l":"καί","s":"2532","m":"CONJ","tr":"καί"},{"t":"τοῖς","a":" ","g":"the","l":"ὁ","s":"3588","m":"T-DPN","tr":"τοῖς"},{"t":"τέκνοις","a":" ","g":"children","l":"τέκνον","s":"5043","m":"N-DPN","tr":"τέκνοις"},{"t":"αὐτῆς","a":",","g":"of her","l":"αὐτός","s":"846","m":"P-GSF","tr":"αὐτῆς"},{"t":"οὓς","a":" ","g":"whom","l":"ὅς","s":"3739","m":"R-APM","tr":"οὕς"},{"t":"ἐγὼ","a":" ","g":"I","l":"ἐγώ","s":"1473","m":"P-1NS","tr":"ἐγώ"},{"t":"ἀγαπῶ","a":" ","g":"love","l":"ἀγαπάω","s":"25","m":"V-PAI-1S","tr":"ἀγαπῶ"},{"t":"ἐν","a":" ","g":"in","l":"ἐν","s":"1722","m":"PREP","tr":"ἐν"},{"t":"ἀληθείᾳ","a":",","g":"truth","l":"ἀλήθεια","s":"225","m":"N-DSF","tr":"ἀληθείᾳ"},{"t":"καὶ","a":" ","g":"and","l":"καί","s":"2532","m":"CONJ","tr":"καί"},{"t":"οὐκ","a":" ","g":"not","l":"οὐ","s":"3756","m":"PRT-N","tr":"οὐκ"},{"t":"ἐγὼ","a":" ","g":"I","l":"ἐγώ","s":"1473","m":"P-1NS","tr":"ἐγώ"},{"t":"μόνος","a":" ","g":"only","l":"μόνος","s":"3441","m":"A-NSM","tr":"μόνος"},{"t":"ἀλλὰ","a":" ","g":"but","l":"ἀλλά","s":"235","m":"CONJ","tr":"ἀλλά"},{"t":"καὶ","a":" ","g":"also","l":"καί","s":"2532","m":"CONJ","tr":"καί"},{"t":"πάντες","a":" ","g":"all","l":"πᾶς","s":"3956","m":"A-NPM","tr":"πάντες"},{"t":"οἱ","a":" ","g":"those","l":"ὁ","s":"3588","m":"T-NPM","tr":"οἱ"},{"t":"ἐγνωκότες","a":" ","g":"having known","l":"γινώσκω","s":"1097","m":"V-RAP-NPM","tr":"ἐγνωκότες"},{"t":"τὴν","a":" ","g":"the","l":"ὁ","s":"3588","m":"T-ASF","tr":"τήν"},{"t":"ἀλήθειαν","a":",","g":"truth","l":"ἀλήθεια","s":"225","m":"N-ASF","tr":"ἀλήθειαν"}],"1:2":[{"t":"διὰ","a":" ","g":"because of","l":"διά","s":"1223","m":"PREP","tr":"διά"},{"t":"τὴν","a":" ","g":"the","l":"ὁ","s":"3588","m":"T-ASF","tr":"τήν"},{"t":"ἀλήθειαν","a":" ","g":"truth","l":"ἀλήθεια","s":"225","m":"N-ASF","tr":"ἀλήθειαν"},{"t":"τὴν","a":" ","g":"-","l":"ὁ","s":"3588","m":"T-ASF","tr":"τήν"},{"t":"μένουσαν","a":" ","g":"abiding","l":"μένω","s":"3306","m":"V-PAP-ASF","tr":"μένουσαν"},{"t":"ἐν","a":" ","g":"in","l":"ἐν","s":"1722","m":"PREP","tr":"ἐν"},{"t":"ἡμῖν","a":",","g":"us","l":"ἐγώ","s":"1473","m":"P-1DP","tr":"ἡμῖν"},{"t":"καὶ","a":" ","g":"and","l":"καί","s":"2532","m":"CONJ","tr":"καί"},{"t":"μεθ","a":"’","g":"with","l":"μετά","s":"3326","m":"PREP","tr":"μεθ’"},{"t":"ἡμῶν","a":" ","g":"us","l":"ἐγώ","s":"1473","m":"P-1GP","tr":"ἡμῶν"},{"t":"ἔσται","a":" ","g":"that will be","l":"εἰμί","s":"1510","m":"V-FDI-3S","tr":"ἔσται"},{"t":"εἰς","a":" ","g":"to","l":"εἰς","s":"1519","m":"PREP","tr":"εἰς"},{"t":"τὸν","a":" ","g":"the","l":"ὁ","s":"3588","m":"T-ASM","tr":"τόν"},{"t":"αἰῶνα","a":".","g":"age","l":"αἰών","s":"165","m":"N-ASM","tr":"αἰῶνα"}],"1:3":[{"t":"ἔσται","a":" ","g":"Will be","l":"εἰμί","s":"1510","m":"V-FDI-3S","tr":"ἔσται"},{"t":"μεθ","a":"’","g":"with","l":"μετά","s":"3326","m":"PREP","tr":"μεθ’"},{"t":"ἡμῶν","a":" ","g":"us","l":"ἐγώ","s":"1473","m":"P-1GP","tr":"ἡμῶν"},{"t":"χάρις","a":" ","g":"grace","l":"χάρις","s":"5485","m":"N-NSF","tr":"χάρις"},{"t":"ἔλεος","a":" ","g":"mercy","l":"ἔλεος","s":"1656","m":"N-NSN","tr":"ἔλεος"},{"t":"εἰρήνη","a":" ","g":"[and] peace","l":"εἰρήνη","s":"1515","m":"N-NSF","tr":"εἰρήνη"},{"t":"παρὰ","a":" ","g":"from","l":"παρά","s":"3844","m":"PREP","tr":"παρά"},{"t":"Θεοῦ","a":" ","g":"God","l":"θεός","s":"2316","m":"N-GSM","tr":"Θεοῦ"},{"t":"Πατρός","a":",","g":"[the] Father","l":"πατήρ","s":"3962","m":"N-GSM","tr":"Πατρός"},{"t":"καὶ","a":" ","g":"and","l":"καί","s":"2532","m":"CONJ","tr":"καί"},{"t":"παρὰ","a":" ","g":"from","l":"παρά","s":"3844","m":"PREP","tr":"παρά"},{"t":"Ἰησοῦ","a":" ","g":"Jesus","l":"Ἰησοῦς","s":"2424","m":"N-GSM","tr":"Ἰησοῦ"},{"t":"Χριστοῦ","a":" ","g":"Christ","l":"Χριστός","s":"5547","m":"N-GSM","tr":"Χριστοῦ"},{"t":"τοῦ","a":" ","g":"the","l":"ὁ","s":"3588","m":"T-GSM","tr":"τοῦ"},{"t":"Υἱοῦ","a":" ","g":"Son","l":"υἱός","s":"5207","m":"N-GSM","tr":"Υἱοῦ"},{"t":"τοῦ","a":" ","g":"of the","l":"ὁ","s":"3588","m":"T-GSM","tr":"τοῦ"},{"t":"Πατρός","a":",","g":"Father","l":"πατήρ","s":"3962","m":"N-GSM","tr":"Πατρός"},{"t":"ἐν","a":" ","g":"in","l":"ἐν","s":"1722","m":"PREP","tr":"ἐν"},{"t":"ἀληθείᾳ","a":" ","g":"truth","l":"ἀλήθεια","s":"225","m":"N-DSF","tr":"ἀληθείᾳ"},{"t":"καὶ","a":" ","g":"and","l":"καί","s":"2532","m":"CONJ","tr":"καί"},{"t":"ἀγάπῃ","a":".","g":"love","l":"ἀγάπη","s":"26","m":"N-DSF","tr":"ἀγάπῃ"}],"1:4":[{"t":"Ἐχάρην","a":" ","g":"I rejoiced","l":"χαίρω","s":"5463","m":"V-2AOI-1S","tr":"Ἐχάρην"},{"t":"λίαν","a":" ","g":"exceedingly","l":"λίαν","s":"3029","m":"ADV","tr":"λίαν"},{"t":"ὅτι","a":" ","g":"that","l":"ὅτι","s":"3754","m":"CONJ","tr":"ὅτι"},{"t":"εὕρηκα","a":" ","g":"I have found","l":"εὑρίσκω","s":"2147","m":"V-RAI-1S","tr":"εὕρηκα"},{"t":"ἐκ","a":" ","g":"[some] of","l":"ἐκ","s":"1537","m":"PREP","tr":"ἐκ"},{"t":"τῶν","a":" ","g":"the","l":"ὁ","s":"3588","m":"T-GPN","tr":"τῶν"},{"t":"τέκνων","a":" ","g":"children","l":"τέκνον","s":"5043","m":"N-GPN","tr":"τέκνων"},{"t":"σου","a":" ","g":"of you","l":"σύ","s":"4771","m":"P-2GS","tr":"σου"},{"t":"περιπατοῦντας","a":" ","g":"walking","l":"περιπατέω","s":"4043","m":"V-PAP-APM","tr":"περιπατοῦντας"},{"t":"ἐν","a":" ","g":"in","l":"ἐν","s":"1722","m":"PREP","tr":"ἐν"},{"t":"ἀληθείᾳ","a":",","g":"truth","l":"ἀλήθεια","s":"225","m":"N-DSF","tr":"ἀληθείᾳ"},{"t":"καθὼς","a":" ","g":"just as","l":"καθώς","s":"2531","m":"ADV","tr":"καθώς"},{"t":"ἐντολὴν","a":" ","g":"commandment","l":"ἐντολή","s":"1785","m":"N-ASF","tr":"ἐντολήν"},{"t":"ἐλάβομεν","a":" ","g":"we received","l":"λαμβάνω","s":"2983","m":"V-2AAI-1P","tr":"ἐλάβομεν"},{"t":"παρὰ","a":" ","g":"from","l":"παρά","s":"3844","m":"PREP","tr":"παρά"},{"t":"τοῦ","a":" ","g":"the","l":"ὁ","s":"3588","m":"T-GSM","tr":"τοῦ"},{"t":"Πατρός","a":".","g":"Father","l":"πατήρ","s":"3962","m":"N-GSM","tr":"Πατρός"}],"1:5":[{"t":"καὶ","a":" ","g":"And","l":"καί","s":"2532","m":"CONJ","tr":"καί"},{"t":"νῦν","a":" ","g":"now","l":"νῦν","s":"3568","m":"ADV","tr":"νῦν"},{"t":"ἐρωτῶ","a":" ","g":"I implore","l":"ἐρωτάω","s":"2065","m":"V-PAI-1S","tr":"ἐρωτῶ"},{"t":"σε","a":",","g":"you","l":"σύ","s":"4771","m":"P-2AS","tr":"σε"},{"t":"κυρία","a":",","g":"lady","l":"κυρία","s":"2959","m":"N-VSF","tr":"κυρία"},{"t":"οὐχ","a":" ","g":"not","l":"οὐ","s":"3756","m":"PRT-N","tr":"οὐχ"},{"t":"ὡς","a":" ","g":"as","l":"ὡς","s":"5613","m":"ADV","tr":"ὡς"},{"t":"ἐντολὴν","a":" ","g":"a commandment","l":"ἐντολή","s":"1785","m":"N-ASF","tr":"ἐντολήν"},{"t":"γράφων","a":" ","g":"I am writing","l":"γράφω","s":"1125","m":"V-PAP-NSM","tr":"γράφων"},{"t":"σοι","a":" ","g":"to you","l":"σύ","s":"4771","m":"P-2DS","tr":"σοι"},{"t":"καινὴν","a":",","g":"new","l":"καινός","s":"2537","m":"A-ASF","tr":"καινήν"},{"t":"ἀλλὰ","a":" ","g":"but","l":"ἀλλά","s":"235","m":"CONJ","tr":"ἀλλά"},{"t":"ἣν","a":" ","g":"that which","l":"ὅς","s":"3739","m":"R-ASF","tr":"ἥν"},{"t":"εἴχαμεν","a":" ","g":"we have had","l":"ἔχω","s":"2192","m":"V-IAI-1P","tr":"εἴχαμεν"},{"t":"ἀπ","a":"’","g":"from","l":"ἀπό","s":"575","m":"PREP","tr":"ἀπ’"},{"t":"ἀρχῆς","a":",","g":"[the] beginning","l":"ἀρχή","s":"746","m":"N-GSF","tr":"ἀρχῆς"},{"t":"ἵνα","a":" ","g":"that","l":"ἵνα","s":"2443","m":"CONJ","tr":"ἵνα"},{"t":"ἀγαπῶμεν","a":" ","g":"we should love","l":"ἀγαπάω","s":"25","m":"V-PAS-1P","tr":"ἀγαπῶμεν"},{"t":"ἀλλήλους","a":".","g":"one another","l":"ἀλλήλων","s":"240","m":"C-APM","tr":"ἀλλήλους"}],"1:6":[{"t":"καὶ","a":" ","g":"And","l":"καί","s":"2532","m":"CONJ","tr":"καί"},{"t":"αὕτη","a":" ","g":"this","l":"οὗτος","s":"3778","m":"D-NSF","tr":"αὕτη"},{"t":"ἐστὶν","a":" ","g":"is","l":"εἰμί","s":"1510","m":"V-PAI-3S","tr":"ἐστίν"},{"t":"ἡ","a":" ","g":"-","l":"ὁ","s":"3588","m":"T-NSF","tr":"ἡ"},{"t":"ἀγάπη","a":",","g":"love","l":"ἀγάπη","s":"26","m":"N-NSF","tr":"ἀγάπη"},{"t":"ἵνα","a":" ","g":"that","l":"ἵνα","s":"2443","m":"CONJ","tr":"ἵνα"},{"t":"περιπατῶμεν","a":" ","g":"we should walk","l":"περιπατέω","s":"4043","m":"V-PAS-1P","tr":"περιπατῶμεν"},{"t":"κατὰ","a":" ","g":"according to","l":"κατά","s":"2596","m":"PREP","tr":"κατά"},{"t":"τὰς","a":" ","g":"the","l":"ὁ","s":"3588","m":"T-APF","tr":"τάς"},{"t":"ἐντολὰς","a":" ","g":"commandments","l":"ἐντολή","s":"1785","m":"N-APF","tr":"ἐντολάς"},{"t":"αὐτοῦ","a":"·","g":"of Him","l":"αὐτός","s":"846","m":"P-GSM","tr":"αὐτοῦ"},{"t":"αὕτη","a":" ","g":"This","l":"οὗτος","s":"3778","m":"D-NSF","tr":"αὕτη"},{"t":"ἡ","a":" ","g":"the","l":"ὁ","s":"3588","m":"T-NSF","tr":"ἡ"},{"t":"ἐντολή","a":" ","g":"commandment","l":"ἐντολή","s":"1785","m":"N-NSF","tr":"ἐντολή"},{"t":"ἐστιν","a":",","g":"is","l":"εἰμί","s":"1510","m":"V-PAI-3S","tr":"ἐστιν"},{"t":"καθὼς","a":" ","g":"just as","l":"καθώς","s":"2531","m":"ADV","tr":"καθώς"},{"t":"ἠκούσατε","a":" ","g":"you have heard","l":"ἀκούω","s":"191","m":"V-AAI-2P","tr":"ἠκούσατε"},{"t":"ἀπ","a":"’","g":"from","l":"ἀπό","s":"575","m":"PREP","tr":"ἀπ’"},{"t":"ἀρχῆς","a":",","g":"[the] beginning","l":"ἀρχή","s":"746","m":"N-GSF","tr":"ἀρχῆς"},{"t":"ἵνα","a":" ","g":"so that","l":"ἵνα","s":"2443","m":"CONJ","tr":"ἵνα"},{"t":"ἐν","a":" ","g":"in","l":"ἐν","s":"1722","m":"PREP","tr":"ἐν"},{"t":"αὐτῇ","a":" ","g":"it","l":"αὐτός","s":"846","m":"P-DSF","tr":"αὐτῇ"},{"t":"περιπατῆτε","a":".","g":"you should walk","l":"περιπατέω","s":"4043","m":"V-PAS-2P","tr":"περιπατῆτε"}],"1:7":[{"t":"ὅτι","a":" ","g":"For","l":"ὅτι","s":"3754","m":"CONJ","tr":"ὅτι"},{"t":"πολλοὶ","a":" ","g":"many","l":"πολύς","s":"4183","m":"A-NPM","tr":"πολλοί"},{"t":"πλάνοι","a":" ","g":"deceivers","l":"πλάνος","s":"4108","m":"A-NPM","tr":"πλάνοι"},{"t":"ἐξῆλθον","a":" ","g":"have entered","l":"ἐξέρχομαι","s":"1831","m":"V-2AAI-3P","tr":"ἐξῆλθον"},{"t":"εἰς","a":" ","g":"into","l":"εἰς","s":"1519","m":"PREP","tr":"εἰς"},{"t":"τὸν","a":" ","g":"the","l":"ὁ","s":"3588","m":"T-ASM","tr":"τόν"},{"t":"κόσμον","a":",","g":"world","l":"κόσμος","s":"2889","m":"N-ASM","tr":"κόσμον"},{"t":"οἱ","a":" ","g":"those","l":"ὁ","s":"3588","m":"T-NPM","tr":"οἱ"},{"t":"μὴ","a":" ","g":"not","l":"μή","s":"3361","m":"PRT-N","tr":"μή"},{"t":"ὁμολογοῦντες","a":" ","g":"confessing","l":"ὁμολογέω","s":"3670","m":"V-PAP-NPM","tr":"ὁμολογοῦντες"},{"t":"Ἰησοῦν","a":" ","g":"Jesus","l":"Ἰησοῦς","s":"2424","m":"N-ASM","tr":"Ἰησοῦν"},{"t":"Χριστὸν","a":" ","g":"Christ","l":"Χριστός","s":"5547","m":"N-ASM","tr":"Χριστόν"},{"t":"ἐρχόμενον","a":" ","g":"coming","l":"ἔρχομαι","s":"2064","m":"V-PNP-ASM","tr":"ἐρχόμενον"},{"t":"ἐν","a":" ","g":"in","l":"ἐν","s":"1722","m":"PREP","tr":"ἐν"},{"t":"σαρκί","a":"·","g":"flesh","l":"σάρξ","s":"4561","m":"N-DSF","tr":"σαρκί"},{"t":"οὗτός","a":" ","g":"This","l":"οὗτος","s":"3778","m":"D-NSM","tr":"οὗτος"},{"t":"ἐστιν","a":" ","g":"is","l":"εἰμί","s":"1510","m":"V-PAI-3S","tr":"ἐστιν"},{"t":"ὁ","a":" ","g":"the","l":"ὁ","s":"3588","m":"T-NSM","tr":"ὁ"},{"t":"πλάνος","a":" ","g":"deceiver","l":"πλάνος","s":"4108","m":"A-NSM","tr":"πλάνος"},{"t":"καὶ","a":" ","g":"and","l":"καί","s":"2532","m":"CONJ","tr":"καί"},{"t":"ὁ","a":" ","g":"the","l":"ὁ","s":"3588","m":"T-NSM","tr":"ὁ"},{"t":"ἀντίχριστος","a":".","g":"antichrist","l":"ἀντίχριστος","s":"500","m":"N-NSM","tr":"ἀντίχριστος"}],"1:8":[{"t":"βλέπετε","a":" ","g":"Watch","l":"βλέπω","s":"991","m":"V-PAM-2P","tr":"βλέπετε"},{"t":"ἑαυτούς","a":",","g":"yourselves","l":"ἑαυτοῦ","s":"1438","m":"F-2APM","tr":"ἑαυτούς"},{"t":"ἵνα","a":" ","g":"so that","l":"ἵνα","s":"2443","m":"CONJ","tr":"ἵνα"},{"t":"μὴ","a":" ","g":"not","l":"μή","s":"3361","m":"PRT-N","tr":"μή"},{"t":"ἀπολέσητε","a":" ","g":"you should lose","l":"ἀπόλλυμι","s":"622","m":"V-AAS-2P","tr":"ἀπολέσητε"},{"t":"ἃ","a":" ","g":"what things","l":"ὅς","s":"3739","m":"R-APN","tr":"ἅ"},{"t":"ἠργασάμεθα","a":",","g":"we have worked for","l":"ἐργάζομαι","s":"2038","m":"V-ADI-1P","tr":"ἠργασάμεθα"},{"t":"ἀλλὰ","a":" ","g":"but","l":"ἀλλά","s":"235","m":"CONJ","tr":"ἀλλά"},{"t":"μισθὸν","a":" ","g":"a reward","l":"μισθός","s":"3408","m":"N-ASM","tr":"μισθόν"},{"t":"πλήρη","a":" ","g":"full","l":"πλήρης","s":"4134","m":"A-ASM","tr":"πλήρη"},{"t":"ἀπολάβητε","a":".","g":"you may receive","l":"ἀπολαμβάνω","s":"618","m":"V-2AAS-2P","tr":"ἀπολάβητε"}],"1:9":[{"t":"πᾶς","a":" ","g":"Anyone","l":"πᾶς","s":"3956","m":"A-NSM","tr":"πᾶς"},{"t":"ὁ","a":" ","g":"-","l":"ὁ","s":"3588","m":"T-NSM","tr":"ὁ"},{"t":"προάγων","a":" ","g":"going on ahead","l":"προάγω","s":"4254","m":"V-PAP-NSM","tr":"προάγων"},{"t":"καὶ","a":" ","g":"and","l":"καί","s":"2532","m":"CONJ","tr":"καί"},{"t":"μὴ","a":" ","g":"not","l":"μή","s":"3361","m":"PRT-N","tr":"μή"},{"t":"μένων","a":" ","g":"abiding","l":"μένω","s":"3306","m":"V-PAP-NSM","tr":"μένων"},{"t":"ἐν","a":" ","g":"in","l":"ἐν","s":"1722","m":"PREP","tr":"ἐν"},{"t":"τῇ","a":" ","g":"the","l":"ὁ","s":"3588","m":"T-DSF","tr":"τῇ"},{"t":"διδαχῇ","a":" ","g":"teaching","l":"διδαχή","s":"1322","m":"N-DSF","tr":"διδαχῇ"},{"t":"τοῦ","a":" ","g":"-","l":"ὁ","s":"3588","m":"T-GSM","tr":"τοῦ"},{"t":"Χριστοῦ","a":" ","g":"of Christ","l":"Χριστός","s":"5547","m":"N-GSM","tr":"Χριστοῦ"},{"t":"Θεὸν","a":" ","g":"God","l":"θεός","s":"2316","m":"N-ASM","tr":"Θεόν"},{"t":"οὐκ","a":" ","g":"not","l":"οὐ","s":"3756","m":"PRT-N","tr":"οὐκ"},{"t":"ἔχει","a":"·","g":"has","l":"ἔχω","s":"2192","m":"V-PAI-3S","tr":"ἔχει"},{"t":"ὁ","a":" ","g":"The [one]","l":"ὁ","s":"3588","m":"T-NSM","tr":"ὁ"},{"t":"μένων","a":" ","g":"abiding","l":"μένω","s":"3306","m":"V-PAP-NSM","tr":"μένων"},{"t":"ἐν","a":" ","g":"in","l":"ἐν","s":"1722","m":"PREP","tr":"ἐν"},{"t":"τῇ","a":" ","g":"the","l":"ὁ","s":"3588","m":"T-DSF","tr":"τῇ"},{"t":"διδαχῇ","a":",","g":"teaching","l":"διδαχή","s":"1322","m":"N-DSF","tr":"διδαχῇ"},{"t":"οὗτος","a":" ","g":"this [one]","l":"οὗτος","s":"3778","m":"D-NSM","tr":"οὗτος"},{"t":"καὶ","a":" ","g":"both","l":"καί","s":"2532","m":"CONJ","tr":"καί"},{"t":"τὸν","a":" ","g":"the","l":"ὁ","s":"3588","m":"T-ASM","tr":"τόν"},{"t":"Πατέρα","a":" ","g":"Father","l":"πατήρ","s":"3962","m":"N-ASM","tr":"Πατέρα"},{"t":"καὶ","a":" ","g":"and","l":"καί","s":"2532","m":"CONJ","tr":"καί"},{"t":"τὸν","a":" ","g":"the","l":"ὁ","s":"3588","m":"T-ASM","tr":"τόν"},{"t":"Υἱὸν","a":" ","g":"Son","l":"υἱός","s":"5207","m":"N-ASM","tr":"Υἱόν"},{"t":"ἔχει","a":".","g":"has","l":"ἔχω","s":"2192","m":"V-PAI-3S","tr":"ἔχει"}],"1:10":[{"t":"εἴ","a":" ","g":"If","l":"εἰ","s":"1487","m":"COND","tr":"εἴ"},{"t":"τις","a":" ","g":"anyone","l":"τὶς","s":"5100","m":"X-NSM","tr":"τις"},{"t":"ἔρχεται","a":" ","g":"comes","l":"ἔρχομαι","s":"2064","m":"V-PNI-3S","tr":"ἔρχεται"},{"t":"πρὸς","a":" ","g":"to","l":"πρός","s":"4314","m":"PREP","tr":"πρός"},{"t":"ὑμᾶς","a":" ","g":"you","l":"σύ","s":"4771","m":"P-2AP","tr":"ὑμᾶς"},{"t":"καὶ","a":" ","g":"and","l":"καί","s":"2532","m":"CONJ","tr":"καί"},{"t":"ταύτην","a":" ","g":"this","l":"οὗτος","s":"3778","m":"D-ASF","tr":"ταύτην"},{"t":"τὴν","a":" ","g":"-","l":"ὁ","s":"3588","m":"T-ASF","tr":"τήν"},{"t":"διδαχὴν","a":" ","g":"teaching","l":"διδαχή","s":"1322","m":"N-ASF","tr":"διδαχήν"},{"t":"οὐ","a":" ","g":"not","l":"οὐ","s":"3756","m":"PRT-N","tr":"οὐ"},{"t":"φέρει","a":",","g":"does bring","l":"φέρω","s":"5342","m":"V-PAI-3S","tr":"φέρει"},{"t":"μὴ","a":" ","g":"not","l":"μή","s":"3361","m":"PRT-N","tr":"μή"},{"t":"λαμβάνετε","a":" ","g":"receive","l":"λαμβάνω","s":"2983","m":"V-PAM-2P","tr":"λαμβάνετε"},{"t":"αὐτὸν","a":" ","g":"him","l":"αὐτός","s":"846","m":"P-ASM","tr":"αὐτόν"},{"t":"εἰς","a":" ","g":"into","l":"εἰς","s":"1519","m":"PREP","tr":"εἰς"},{"t":"οἰκίαν","a":",","g":"[the] house","l":"οἰκία","s":"3614","m":"N-ASF","tr":"οἰκίαν"},{"t":"καὶ","a":" ","g":"and","l":"καί","s":"2532","m":"CONJ","tr":"καί"},{"t":"χαίρειν","a":" ","g":"to rejoice","l":"χαίρω","s":"5463","m":"V-PAN","tr":"χαίρειν"},{"t":"αὐτῷ","a":" ","g":"him","l":"αὐτός","s":"846","m":"P-DSM","tr":"αὐτῷ"},{"t":"μὴ","a":" ","g":"not","l":"μή","s":"3361","m":"PRT-N","tr":"μή"},{"t":"λέγετε","a":"·","g":"tell","l":"λέγω","s":"3004","m":"V-PAM-2P","tr":"λέγετε"}],"1:11":[{"t":"ὁ","a":" ","g":"the [one]","l":"ὁ","s":"3588","m":"T-NSM","tr":"ὁ"},{"t":"λέγων","a":" ","g":"telling","l":"λέγω","s":"3004","m":"V-PAP-NSM","tr":"λέγων"},{"t":"γὰρ","a":" ","g":"for","l":"γάρ","s":"1063","m":"CONJ","tr":"γάρ"},{"t":"αὐτῷ","a":" ","g":"him","l":"αὐτός","s":"846","m":"P-DSM","tr":"αὐτῷ"},{"t":"χαίρειν","a":" ","g":"to rejoice","l":"χαίρω","s":"5463","m":"V-PAN","tr":"χαίρειν"},{"t":"κοινωνεῖ","a":" ","g":"partakes","l":"κοινωνέω","s":"2841","m":"V-PAI-3S","tr":"κοινωνεῖ"},{"t":"τοῖς","a":" ","g":"in the","l":"ὁ","s":"3588","m":"T-DPN","tr":"τοῖς"},{"t":"ἔργοις","a":" ","g":"works","l":"ἔργον","s":"2041","m":"N-DPN","tr":"ἔργοις"},{"t":"αὐτοῦ","a":" ","g":"of him","l":"αὐτός","s":"846","m":"P-GSM","tr":"αὐτοῦ"},{"t":"τοῖς","a":" ","g":"-","l":"ὁ","s":"3588","m":"T-DPN","tr":"τοῖς"},{"t":"πονηροῖς","a":".","g":"evil","l":"πονηρός","s":"4190","m":"A-DPN","tr":"πονηροῖς"}],"1:12":[{"t":"Πολλὰ","a":" ","g":"Many things","l":"πολύς","s":"4183","m":"A-APN","tr":"Πολλά"},{"t":"ἔχων","a":" ","g":"having","l":"ἔχω","s":"2192","m":"V-PAP-NSM","tr":"ἔχων"},{"t":"ὑμῖν","a":" ","g":"to you","l":"σύ","s":"4771","m":"P-2DP","tr":"ὑμῖν"},{"t":"γράφειν","a":" ","g":"to write","l":"γράφω","s":"1125","m":"V-PAN","tr":"γράφειν"},{"t":"οὐκ","a":" ","g":"not","l":"οὐ","s":"3756","m":"PRT-N","tr":"οὐκ"},{"t":"ἐβουλήθην","a":" ","g":"I purposed","l":"βούλομαι","s":"1014","m":"V-AOI-1S","tr":"ἐβουλήθην"},{"t":"διὰ","a":" ","g":"with","l":"διά","s":"1223","m":"PREP","tr":"διά"},{"t":"χάρτου","a":" ","g":"paper","l":"χάρτης","s":"5489","m":"N-GSM","tr":"χάρτου"},{"t":"καὶ","a":" ","g":"and","l":"καί","s":"2532","m":"CONJ","tr":"καί"},{"t":"μέλανος","a":",","g":"ink","l":"μέλας","s":"3188","m":"A-GSN","tr":"μέλανος"},{"t":"ἀλλὰ","a":" ","g":"but","l":"ἀλλά","s":"235","m":"CONJ","tr":"ἀλλά"},{"t":"ἐλπίζω","a":" ","g":"I hope","l":"ἐλπίζω","s":"1679","m":"V-PAI-1S","tr":"ἐλπίζω"},{"t":"γενέσθαι","a":" ","g":"to come","l":"γίνομαι","s":"1096","m":"V-2ADN","tr":"γενέσθαι"},{"t":"πρὸς","a":" ","g":"to","l":"πρός","s":"4314","m":"PREP","tr":"πρός"},{"t":"ὑμᾶς","a":" ","g":"you","l":"σύ","s":"4771","m":"P-2AP","tr":"ὑμᾶς"},{"t":"καὶ","a":" ","g":"and","l":"καί","s":"2532","m":"CONJ","tr":"καί"},{"t":"στόμα","a":" ","g":"mouth","l":"στόμα","s":"4750","m":"N-ASN","tr":"στόμα"},{"t":"πρὸς","a":" ","g":"to","l":"πρός","s":"4314","m":"PREP","tr":"πρός"},{"t":"στόμα","a":" ","g":"mouth","l":"στόμα","s":"4750","m":"N-ASN","tr":"στόμα"},{"t":"λαλῆσαι","a":",","g":"to speak","l":"λαλέω","s":"2980","m":"V-AAN","tr":"λαλῆσαι"},{"t":"ἵνα","a":" ","g":"so that","l":"ἵνα","s":"2443","m":"CONJ","tr":"ἵνα"},{"t":"ἡ","a":" ","g":"the","l":"ὁ","s":"3588","m":"T-NSF","tr":"ἡ"},{"t":"χαρὰ","a":" ","g":"joy","l":"χαρά","s":"5479","m":"N-NSF","tr":"χαρά"},{"t":"ἡμῶν","a":" ","g":"of us","l":"ἐγώ","s":"1473","m":"P-1GP","tr":"ἡμῶν"},{"t":"πεπληρωμένη","a":" ","g":"having been completed","l":"πληρόω","s":"4137","m":"V-RPP-NSF","tr":"πεπληρωμένη"},{"t":"ᾖ","a":".","g":"may be","l":"εἰμί","s":"1510","m":"V-PAS-3S","tr":"ᾖ"}],"1:13":[{"t":"Ἀσπάζεταί","a":" ","g":"Greet","l":"ἀσπάζομαι","s":"782","m":"V-PNI-3S","tr":"Ἀσπάζεται"},{"t":"σε","a":" ","g":"you","l":"σύ","s":"4771","m":"P-2AS","tr":"σε"},{"t":"τὰ","a":" ","g":"the","l":"ὁ","s":"3588","m":"T-NPN","tr":"τά"},{"t":"τέκνα","a":" ","g":"children","l":"τέκνον","s":"5043","m":"N-NPN","tr":"τέκνα"},{"t":"τῆς","a":" ","g":"of the","l":"ὁ","s":"3588","m":"T-GSF","tr":"τῆς"},{"t":"ἀδελφῆς","a":" ","g":"sister","l":"ἀδελφή","s":"79","m":"N-GSF","tr":"ἀδελφῆς"},{"t":"σου","a":" ","g":"of you","l":"σύ","s":"4771","m":"P-2GS","tr":"σου"},{"t":"τῆς","a":" ","g":"-","l":"ὁ","s":"3588","m":"T-GSF","tr":"τῆς"},{"t":"ἐκλεκτῆς","a":".","g":"elect","l":"ἐκλεκτός","s":"1588","m":"A-GSF","tr":"ἐκλεκτῆς"}]}}