{"book":"Jonah","lang":"hebrew","verses":{"1:1":[{"t":"וַֽ","a":"","g":"and","l":"וְ","s":"2050","m":"C","tr":"wa"},{"t":"יְהִי֙","a":" ","g":"it.came","l":"הָיָה","s":"1961","m":"Vqw3ms","tr":"yəhî"},{"t":"דְּבַר","a":"־","g":"the.word","l":"דָּבָר","s":"1697","m":"Ncmsc","tr":"dəḇar-"},{"t":"יְהוָ֔ה","a":" ","g":"of.Yahweh","l":"יהוה","s":"3068","m":"Np","tr":"yəhwāh"},{"t":"אֶל","a":"־","g":"to","l":"אֶל","s":"413","m":"R","tr":"ʾel-"},{"t":"יוֹנָ֥ה","a":" ","g":"Jonah","l":"יוֹנָה","s":"3124","m":"Np","tr":"yônāh"},{"t":"בֶן","a":"־","g":"the.son","l":"בֵּן","s":"1121","m":"Ncmsc","tr":"ḇen-"},{"t":"אֲמִתַּ֖י","a":" ","g":"of.Amittai","l":"אֲמִתַּי","s":"573","m":"Np","tr":"ʾămittay"},{"t":"לֵ","a":"","g":"(cmp)","l":"לְ","s":"3807","m":"R","tr":"lē"},{"t":"אמֹֽר","a":"׃","g":"saying","l":"אָמַר","s":"559","m":"Vqc","tr":"ʾmōr:"}],"1:2":[{"t":"ק֠וּם","a":" ","g":"arise","l":"קוּם","s":"6965","m":"Vqv2ms","tr":"qûm"},{"t":"לֵ֧ךְ","a":" ","g":"go","l":"הלך","s":"1980","m":"Vqv2ms","tr":"lēḵ"},{"t":"אֶל","a":"־","g":"to","l":"אֶל","s":"413","m":"R","tr":"ʾel-"},{"t":"נִֽינְוֵ֛ה","a":" ","g":"Nineveh","l":"נִינְוֵה","s":"5210","m":"Np","tr":"niynəwēh"},{"t":"הָ","a":"","g":"the","l":"הַ","s":"1886","m":"Td","tr":"hā"},{"t":"עִ֥יר","a":" ","g":"city","l":"עִיר","s":"5892","m":"Ncfsa","tr":"ʿiyr"},{"t":"הַ","a":"","g":"(the)","l":"הַ","s":"1886","m":"Td","tr":"ha"},{"t":"גְּדוֹלָ֖ה","a":" ","g":"great","l":"גָּדוֹל","s":"1419","m":"Aafsa","tr":"gəḏôlāh"},{"t":"וּ","a":"","g":"and","l":"וְ","s":"2050","m":"C","tr":"û"},{"t":"קְרָ֣א","a":" ","g":"call.out","l":"קָרָא","s":"7121","m":"Vqv2ms","tr":"qərāʾ"},{"t":"עָלֶ֑י","a":"","g":"on","l":"עַל","s":"5921","m":"R","tr":""},{"t":"הָ","a":" ","g":"it","l":"הוּא","s":"1886","m":"Sp3fs","tr":""},{"t":"כִּֽי","a":"־","g":"(dm)","l":"כִּי","s":"3588","m":"C","tr":"kiy-"},{"t":"עָלְתָ֥ה","a":" ","g":"it.has.come.up","l":"עָלָה","s":"5927","m":"Vqp3fs","tr":"ʿāləṯāh"},{"t":"רָעָתָ֖","a":"","g":"wickedness","l":"רָעָה","s":"7451","m":"Ncfsc","tr":""},{"t":"ם","a":" ","g":"their","l":"הוּא","s":"3963","m":"Sp3mp","tr":""},{"t":"לְ","a":"","g":"before","l":"לְ","s":"3807","m":"R","tr":"lə"},{"t":"פָנָֽ","a":"","g":"","l":"פָּנֶה","s":"6440","m":"Ncbpc","tr":""},{"t":"י","a":"׃","g":"me","l":"הוּא","s":"2967","m":"Sp1cs","tr":""}],"1:3":[{"t":"וַ","a":"","g":"and","l":"וְ","s":"2050","m":"C","tr":"wa"},{"t":"יָּ֤קָם","a":" ","g":"he.arose","l":"קוּם","s":"6965","m":"Vqw3ms","tr":"yyāqām"},{"t":"יוֹנָה֙","a":" ","g":"Jonah","l":"יוֹנָה","s":"3124","m":"Np","tr":"yônāh"},{"t":"לִ","a":"","g":"to","l":"לְ","s":"3807","m":"R","tr":"li"},{"t":"בְרֹ֣חַ","a":" ","g":"flee","l":"בָּרַח","s":"1272","m":"Vqc","tr":"ḇərōᵃḥ"},{"t":"תַּרְשִׁ֔ישָׁ","a":"","g":"to","l":"תַּרְשִׁישׁ","s":"8659","m":"Np","tr":""},{"t":"ה","a":" ","g":"Tarshish","l":"ה","s":"1886","m":"Sd","tr":""},{"t":"מִ","a":"","g":"from","l":"מִן","s":"4480","m":"R","tr":"mi"},{"t":"לִּ","a":"","g":"","l":"לְ","s":"3807","m":"R","tr":"lli"},{"t":"פְנֵ֖י","a":" ","g":"before","l":"פָּנֶה","s":"6440","m":"Ncbpc","tr":"p̄ənēy"},{"t":"יְהוָ֑ה","a":" ","g":"Yahweh","l":"יהוה","s":"3068","m":"Np","tr":"yəhwāh"},{"t":"וַ","a":"","g":"and","l":"וְ","s":"2050","m":"C","tr":"wa"},{"t":"יֵּ֨רֶד","a":" ","g":"he.went.down","l":"יָרַד","s":"3381","m":"Vqw3ms","tr":"yyēreḏ"},{"t":"יָפ֜וֹ","a":" ","g":"Joppa","l":"יָפוֹ","s":"3305","m":"Np","tr":"yāp̄ô"},{"t":"וַ","a":"","g":"and","l":"וְ","s":"2050","m":"C","tr":"wa"},{"t":"יִּמְצָ֥א","a":" ","g":"he.found","l":"מָצָא","s":"4672","m":"Vqw3ms","tr":"yyimṣāʾ"},{"t":"אָנִיָּ֣ה","a":"׀","g":"a.ship","l":"אֳנִיָּה","s":"591","m":"Ncfsa","tr":"ʾāniyyāh"},{"t":"בָּאָ֣ה","a":" ","g":"[which.was].about.to.go","l":"בּוֹא","s":"935","m":"Vqrfsa","tr":"bāʾāh"},{"t":"תַרְשִׁ֗ישׁ","a":" ","g":"Tarshish","l":"תַּרְשִׁישׁ","s":"8659","m":"Np","tr":"ṯaršiyš"},{"t":"וַ","a":"","g":"and","l":"וְ","s":"2050","m":"C","tr":"wa"},{"t":"יִּתֵּ֨ן","a":" ","g":"he.gave","l":"נָתַן","s":"5414","m":"Vqw3ms","tr":"yyittēn"},{"t":"שְׂכָרָ֜","a":"","g":"fare","l":"שָׂכָר","s":"7939","m":"Ncmsc","tr":""},{"t":"הּ","a":" ","g":"its","l":"הוּא","s":"1886","m":"Sp3fs","tr":""},{"t":"וַ","a":"","g":"and","l":"וְ","s":"2050","m":"C","tr":"wa"},{"t":"יֵּ֤רֶד","a":" ","g":"he.went.down","l":"יָרַד","s":"3381","m":"Vqw3ms","tr":"yyēreḏ"},{"t":"בָּ","a":"","g":"in","l":"בְּ","s":"871","m":"R","tr":""},{"t":"הּ֙","a":" ","g":"it","l":"הוּא","s":"1886","m":"Sp3fs","tr":""},{"t":"לָ","a":"","g":"to","l":"לְ","s":"3807","m":"R","tr":"lā"},{"t":"ב֤וֹא","a":" ","g":"go","l":"בּוֹא","s":"935","m":"Vqc","tr":"ḇôʾ"},{"t":"עִמָּ","a":"","g":"with","l":"עִם","s":"5973","m":"R","tr":""},{"t":"הֶם֙","a":" ","g":"them","l":"הוּא","s":"3963","m":"Sp3mp","tr":""},{"t":"תַּרְשִׁ֔ישָׁ","a":"","g":"to","l":"תַּרְשִׁישׁ","s":"8659","m":"Np","tr":""},{"t":"ה","a":" ","g":"Tarshish","l":"ה","s":"1886","m":"Sd","tr":""},{"t":"מִ","a":"","g":"from","l":"מִן","s":"4480","m":"R","tr":"mi"},{"t":"לִּ","a":"","g":"","l":"לְ","s":"3807","m":"R","tr":"lli"},{"t":"פְנֵ֖י","a":" ","g":"before","l":"פָּנֶה","s":"6440","m":"Ncbpc","tr":"p̄ənēy"},{"t":"יְהוָֽה","a":"׃","g":"Yahweh","l":"יהוה","s":"3068","m":"Np","tr":"yəhwāh:"}],"1:4":[{"t":"וַֽ","a":"","g":"and","l":"וְ","s":"2050","m":"C","tr":"wa"},{"t":"יהוָ֗ה","a":" ","g":"Yahweh","l":"יהוה","s":"3068","m":"Np","tr":"yhwāh"},{"t":"הֵטִ֤יל","a":" ","g":"he.hurled","l":"טוּל","s":"2904","m":"Vhp3ms","tr":"hēṭiyl"},{"t":"רֽוּחַ","a":"־","g":"a.wind","l":"רוּחַ","s":"7307","m":"Ncbsa","tr":"rûᵃḥ-"},{"t":"גְּדוֹלָה֙","a":" ","g":"great","l":"גָּדוֹל","s":"1419","m":"Aafsa","tr":"gəḏôlāh"},{"t":"אֶל","a":"־","g":"to","l":"אֶל","s":"413","m":"R","tr":"ʾel-"},{"t":"הַ","a":"","g":"the","l":"הַ","s":"1886","m":"Td","tr":"ha"},{"t":"יָּ֔ם","a":" ","g":"sea","l":"יָם","s":"3220","m":"Ncmsa","tr":"yyām"},{"t":"וַ","a":"","g":"and","l":"וְ","s":"2050","m":"C","tr":"wa"},{"t":"יְהִ֥י","a":" ","g":"it.was","l":"הָיָה","s":"1961","m":"Vqw3ms","tr":"yəhiy"},{"t":"סַֽעַר","a":"־","g":"a.storm","l":"סַעַר","s":"5591","m":"Ncmsa","tr":"saʿar-"},{"t":"גָּד֖וֹל","a":" ","g":"great","l":"גָּדוֹל","s":"1419","m":"Aamsa","tr":"gāḏôl"},{"t":"בַּ","a":"","g":"on","l":"בְּ","s":"871","m":"Rd","tr":"ba"},{"t":"","a":"","g":"the","l":"הַ","s":"1886","m":"Td","tr":"–"},{"t":"יָּ֑ם","a":" ","g":"sea","l":"יָם","s":"3220","m":"Ncmsa","tr":"yyām"},{"t":"וְ","a":"","g":"and","l":"וְ","s":"2050","m":"C","tr":"wə"},{"t":"הָ֣","a":"","g":"the","l":"הַ","s":"1886","m":"Td","tr":"hā"},{"t":"אֳנִיָּ֔ה","a":" ","g":"ship","l":"אֳנִיָּה","s":"591","m":"Ncfsa","tr":"ʾŏniyyāh"},{"t":"חִשְּׁבָ֖ה","a":" ","g":"it.thought","l":"חָשַׁב","s":"2803","m":"Vpp3fs","tr":"ḥiššəḇāh"},{"t":"לְ","a":"","g":"to","l":"לְ","s":"3807","m":"R","tr":"lə"},{"t":"הִשָּׁבֵֽר","a":"׃","g":"be.broken","l":"שָׁבַר","s":"7665","m":"VNc","tr":"hiššāḇēr:"}],"1:5":[{"t":"וַ","a":"","g":"and","l":"וְ","s":"2050","m":"C","tr":"wa"},{"t":"יִּֽירְא֣וּ","a":" ","g":"they.were.afraid","l":"יָרֵא","s":"3372","m":"Vqw3mp","tr":"yyiyrəʾû"},{"t":"הַ","a":"","g":"the","l":"הַ","s":"1886","m":"Td","tr":"ha"},{"t":"מַּלָּחִ֗ים","a":" ","g":"mariners","l":"מַלָּח","s":"4419","m":"Ncmpa","tr":"mmallāḥiym"},{"t":"וַֽ","a":"","g":"and","l":"וְ","s":"2050","m":"C","tr":"wa"},{"t":"יִּזְעֲקוּ֮","a":" ","g":"they.cried.for.help","l":"זָעַק","s":"2199","m":"Vqw3mp","tr":"yyizʿăqû"},{"t":"אִ֣ישׁ","a":" ","g":"each","l":"אִישׁ","s":"376","m":"Ncmsa","tr":"ʾiyš"},{"t":"אֶל","a":"־","g":"to","l":"אֶל","s":"413","m":"R","tr":"ʾel-"},{"t":"אֱלֹהָי","a":"","g":"gods","l":"אֱלֹהִים","s":"430","m":"Ncmpc","tr":""},{"t":"ו֒","a":" ","g":"his","l":"הוּא","s":"2050","m":"Sp3ms","tr":""},{"t":"וַ","a":"","g":"and","l":"וְ","s":"2050","m":"C","tr":"wa"},{"t":"יָּטִ֨לוּ","a":" ","g":"they.hurled","l":"טוּל","s":"2904","m":"Vhw3mp","tr":"yyāṭilû"},{"t":"אֶת","a":"־","g":"(et)","l":"אֵת","s":"853","m":"To","tr":"ʾeṯ-"},{"t":"הַ","a":"","g":"the","l":"הַ","s":"1886","m":"Td","tr":"ha"},{"t":"כֵּלִ֜ים","a":" ","g":"vessels","l":"כְּלִי","s":"3627","m":"Ncmpa","tr":"kēliym"},{"t":"אֲשֶׁ֤ר","a":" ","g":"which","l":"אֲשֶׁר","s":"834","m":"Tr","tr":"ʾăšer"},{"t":"בָּֽ","a":"","g":"[were].in","l":"בְּ","s":"871","m":"Rd","tr":"bā"},{"t":"","a":"","g":"the","l":"הַ","s":"1886","m":"Td","tr":"–"},{"t":"אֳנִיָּה֙","a":" ","g":"ship","l":"אֳנִיָּה","s":"591","m":"Ncfsa","tr":"ʾŏniyyāh"},{"t":"אֶל","a":"־","g":"into","l":"אֶל","s":"413","m":"R","tr":"ʾel-"},{"t":"הַ","a":"","g":"the","l":"הַ","s":"1886","m":"Td","tr":"ha"},{"t":"יָּ֔ם","a":" ","g":"sea","l":"יָם","s":"3220","m":"Ncmsa","tr":"yyām"},{"t":"לְ","a":"","g":"to","l":"לְ","s":"3807","m":"R","tr":"lə"},{"t":"הָקֵ֖ל","a":" ","g":"lighten","l":"קָלַל","s":"7043","m":"Vhc","tr":"hāqēl"},{"t":"מֵֽ","a":"","g":"from","l":"מִן","s":"4480","m":"R","tr":"mē"},{"t":"עֲלֵי","a":"","g":"on","l":"עַל","s":"5921","m":"R","tr":""},{"t":"הֶ֑ם","a":" ","g":"them","l":"הוּא","s":"3963","m":"Sp3mp","tr":""},{"t":"וְ","a":"","g":"and","l":"וְ","s":"2050","m":"C","tr":"wə"},{"t":"יוֹנָ֗ה","a":" ","g":"Jonah","l":"יוֹנָה","s":"3124","m":"Np","tr":"yônāh"},{"t":"יָרַד֙","a":" ","g":"he.had.gone.down","l":"יָרַד","s":"3381","m":"Vqp3ms","tr":"yāraḏ"},{"t":"אֶל","a":"־","g":"into","l":"אֶל","s":"413","m":"R","tr":"ʾel-"},{"t":"יַרְכְּתֵ֣י","a":" ","g":"the.innermost.parts","l":"יַרְכָה","s":"3411","m":"Ncfdc","tr":"yarkəṯēy"},{"t":"הַ","a":"","g":"of","l":"הַ","s":"1886","m":"Td","tr":"ha"},{"t":"סְּפִינָ֔ה","a":" ","g":"the.ship","l":"סְפִינָה","s":"5600","m":"Ncfsa","tr":"ssəp̄înāh"},{"t":"וַ","a":"","g":"and","l":"וְ","s":"2050","m":"C","tr":"wa"},{"t":"יִּשְׁכַּ֖ב","a":" ","g":"he.had.lain.down","l":"שָׁכַב","s":"7901","m":"Vqw3ms","tr":"yyiškaḇ"},{"t":"וַ","a":"","g":"and","l":"וְ","s":"2050","m":"C","tr":"wa"},{"t":"יֵּרָדַֽם","a":"׃","g":"he.had.fallen.asleep","l":"רָדַם","s":"7290","m":"VNw3ms","tr":"yyērāḏam:"}],"1:6":[{"t":"וַ","a":"","g":"and","l":"וְ","s":"2050","m":"C","tr":"wa"},{"t":"יִּקְרַ֤ב","a":" ","g":"he.drew.near","l":"קָרַב","s":"7126","m":"Vqw3ms","tr":"yyiqraḇ"},{"t":"אֵלָי","a":"","g":"to","l":"אֶל","s":"413","m":"R","tr":""},{"t":"ו֙","a":" ","g":"him","l":"הוּא","s":"2050","m":"Sp3ms","tr":""},{"t":"רַ֣ב","a":" ","g":"the.chief","l":"רַב","s":"7227","m":"Ncmsc","tr":"raḇ"},{"t":"הַ","a":"","g":"of","l":"הַ","s":"1886","m":"Td","tr":"ha"},{"t":"חֹבֵ֔ל","a":" ","g":"the.sailor[s]","l":"חֹבֵל","s":"2259","m":"Ncmsa","tr":"ḥōḇēl"},{"t":"וַ","a":"","g":"and","l":"וְ","s":"2050","m":"C","tr":"wa"},{"t":"יֹּ֥אמֶר","a":" ","g":"he.said","l":"אָמַר","s":"559","m":"Vqw3ms","tr":"yyōʾmer"},{"t":"ל֖","a":"","g":"to","l":"לְ","s":"3807","m":"R","tr":""},{"t":"וֹ","a":" ","g":"him","l":"הוּא","s":"2050","m":"Sp3ms","tr":""},{"t":"מַה","a":"־","g":"what?","l":"מָה","s":"4100","m":"Ti","tr":"mah-"},{"t":"לְּ","a":"","g":"[is].to","l":"לְ","s":"3807","m":"R","tr":""},{"t":"ךָ֣","a":" ","g":"you","l":"הוּא","s":"3509","m":"Sp2ms","tr":""},{"t":"נִרְדָּ֑ם","a":" ","g":"sleeping","l":"רָדַם","s":"7290","m":"VNrmsa","tr":"nirdām"},{"t":"ק֚וּם","a":" ","g":"arise","l":"קוּם","s":"6965","m":"Vqv2ms","tr":"qûm"},{"t":"קְרָ֣א","a":" ","g":"call","l":"קָרָא","s":"7121","m":"Vqv2ms","tr":"qərāʾ"},{"t":"אֶל","a":"־","g":"to","l":"אֶל","s":"413","m":"R","tr":"ʾel-"},{"t":"אֱלֹהֶ֔י","a":"","g":"god","l":"אֱלֹהִים","s":"430","m":"Ncmpc","tr":""},{"t":"ךָ","a":" ","g":"your","l":"הוּא","s":"3509","m":"Sp2ms","tr":""},{"t":"אוּלַ֞י","a":" ","g":"perhaps","l":"אוּלַי","s":"194","m":"D","tr":"ʾûlay"},{"t":"יִתְעַשֵּׁ֧ת","a":" ","g":"he.will.give.thought","l":"עָשַׁת","s":"6245","m":"Vti3ms","tr":"yiṯʿaššēṯ"},{"t":"הָ","a":"","g":"the","l":"הַ","s":"1886","m":"Td","tr":"hā"},{"t":"אֱלֹהִ֛ים","a":" ","g":"god","l":"אֱלֹהִים","s":"430","m":"Ncmpa","tr":"ʾĕlōhiym"},{"t":"לָ֖","a":"","g":"to","l":"לְ","s":"3807","m":"R","tr":""},{"t":"נוּ","a":" ","g":"us","l":"הוּא","s":"5105","m":"Sp1cp","tr":""},{"t":"וְ","a":"","g":"and","l":"וְ","s":"2050","m":"C","tr":"wə"},{"t":"לֹ֥א","a":" ","g":"not","l":"לֹא","s":"3808","m":"Tn","tr":"lōʾ"},{"t":"נֹאבֵֽד","a":"׃","g":"we.will.perish","l":"אָבַד","s":"6","m":"Vqi1cp","tr":"nōʾḇēḏ:"}],"1:7":[{"t":"וַ","a":"","g":"and","l":"וְ","s":"2050","m":"C","tr":"wa"},{"t":"יֹּאמְר֞וּ","a":" ","g":"they.said","l":"אָמַר","s":"559","m":"Vqw3mp","tr":"yyōʾmərû"},{"t":"אִ֣ישׁ","a":" ","g":"each","l":"אִישׁ","s":"376","m":"Ncmsa","tr":"ʾiyš"},{"t":"אֶל","a":"־","g":"to","l":"אֶל","s":"413","m":"R","tr":"ʾel-"},{"t":"רֵעֵ֗","a":"","g":"neighbor","l":"רֵעַ","s":"7453","m":"Ncmsc","tr":""},{"t":"הוּ","a":" ","g":"his","l":"הוּא","s":"1930","m":"Sp3ms","tr":""},{"t":"לְכוּ֙","a":" ","g":"come","l":"הלך","s":"1980","m":"Vqv2mp","tr":"ləḵû"},{"t":"וְ","a":"","g":"and","l":"וְ","s":"2050","m":"C","tr":"wə"},{"t":"נַפִּ֣ילָה","a":" ","g":"let.us.cast","l":"נָפַל","s":"5307","m":"Vhh1cp","tr":"nappiylâ"},{"t":"גֽוֹרָל֔וֹת","a":" ","g":"lots","l":"גּוֹרָל","s":"1486","m":"Ncmpa","tr":"ḡôrālôṯ"},{"t":"וְ","a":"","g":"so","l":"וְ","s":"2050","m":"C","tr":"wə"},{"t":"נֵ֣דְעָ֔ה","a":" ","g":"that.we.may.know","l":"יָדַע","s":"3045","m":"Vqh1cp","tr":"nēḏəʿāh"},{"t":"בְּ","a":"","g":"by","l":"בְּ","s":"871","m":"R","tr":"bə"},{"t":"שֶׁ","a":"","g":"which","l":"שֶׁ","s":"7578","m":"Tr","tr":"še"},{"t":"לְּ","a":"","g":"of","l":"לְ","s":"3807","m":"R","tr":"llə"},{"t":"מִ֛י","a":" ","g":"whom?","l":"מִי","s":"4310","m":"Ti","tr":"miy"},{"t":"הָ","a":"","g":"the","l":"הַ","s":"1886","m":"Td","tr":"hā"},{"t":"רָעָ֥ה","a":" ","g":"evil","l":"רָעָה","s":"7451","m":"Ncfsa","tr":"rāʿāh"},{"t":"הַ","a":"","g":"(the)","l":"הַ","s":"1886","m":"Td","tr":"ha"},{"t":"זֹּ֖את","a":" ","g":"this","l":"זֹאת","s":"2063","m":"Pdxfs","tr":"zzōʾṯ"},{"t":"לָ֑","a":"","g":"[belongs].to","l":"לְ","s":"3807","m":"R","tr":""},{"t":"נוּ","a":" ","g":"us","l":"הוּא","s":"5105","m":"Sp1cp","tr":""},{"t":"וַ","a":"","g":"and","l":"וְ","s":"2050","m":"C","tr":"wa"},{"t":"יַּפִּ֨לוּ֙","a":" ","g":"they.cast","l":"נָפַל","s":"5307","m":"Vhw3mp","tr":"yyappilû"},{"t":"גּֽוֹרָל֔וֹת","a":" ","g":"lots","l":"גּוֹרָל","s":"1486","m":"Ncmpa","tr":"gôrālôṯ"},{"t":"וַ","a":"","g":"and","l":"וְ","s":"2050","m":"C","tr":"wa"},{"t":"יִּפֹּ֥ל","a":" ","g":"it.fell","l":"נָפַל","s":"5307","m":"Vqw3ms","tr":"yyippōl"},{"t":"הַ","a":"","g":"the","l":"הַ","s":"1886","m":"Td","tr":"ha"},{"t":"גּוֹרָ֖ל","a":" ","g":"lot","l":"גּוֹרָל","s":"1486","m":"Ncmsa","tr":"gôrāl"},{"t":"עַל","a":"־","g":"on","l":"עַל","s":"5921","m":"R","tr":"ʿal-"},{"t":"יוֹנָֽה","a":"׃","g":"Jonah","l":"יוֹנָה","s":"3124","m":"Np","tr":"yônāh:"}],"1:8":[{"t":"וַ","a":"","g":"and","l":"וְ","s":"2050","m":"C","tr":"wa"},{"t":"יֹּאמְר֣וּ","a":" ","g":"they.said","l":"אָמַר","s":"559","m":"Vqw3mp","tr":"yyōʾmərû"},{"t":"אֵלָ֔י","a":"","g":"to","l":"אֶל","s":"413","m":"R","tr":""},{"t":"ו","a":" ","g":"him","l":"הוּא","s":"2050","m":"Sp3ms","tr":""},{"t":"הַגִּידָ","a":"","g":"tell","l":"נָגַד","s":"5046","m":"Vhv2ms","tr":""},{"t":"ה","a":"־","g":"","l":"ה","s":"1886","m":"Sh","tr":""},{"t":"נָּ֣א","a":" ","g":"please","l":"נָא","s":"4994","m":"Tj","tr":"nnāʾ"},{"t":"לָ֔","a":"","g":"to","l":"לְ","s":"3807","m":"R","tr":""},{"t":"נוּ","a":" ","g":"us","l":"הוּא","s":"5105","m":"Sp1cp","tr":""},{"t":"בַּ","a":"","g":"because","l":"בְּ","s":"871","m":"R","tr":"ba"},{"t":"אֲשֶׁ֛ר","a":" ","g":"account of that","l":"אֲשֶׁר","s":"834","m":"Tr","tr":"ʾăšer"},{"t":"לְ","a":"","g":"of","l":"לְ","s":"3807","m":"R","tr":"lə"},{"t":"מִי","a":"־","g":"whom?","l":"מִי","s":"4310","m":"Ti","tr":"mî-"},{"t":"הָ","a":"","g":"the","l":"הַ","s":"1886","m":"Td","tr":"hā"},{"t":"רָעָ֥ה","a":" ","g":"evil","l":"רָעָה","s":"7451","m":"Ncfsa","tr":"rāʿāh"},{"t":"הַ","a":"","g":"(the)","l":"הַ","s":"1886","m":"Td","tr":"ha"},{"t":"זֹּ֖את","a":" ","g":"this","l":"זֹאת","s":"2063","m":"Pdxfs","tr":"zzōʾṯ"},{"t":"לָ֑","a":"","g":"[belongs].to","l":"לְ","s":"3807","m":"R","tr":""},{"t":"נוּ","a":" ","g":"us","l":"הוּא","s":"5105","m":"Sp1cp","tr":""},{"t":"מַה","a":"־","g":"what?","l":"מָה","s":"4100","m":"Ti","tr":"mah-"},{"t":"מְּלַאכְתְּ","a":"","g":"occupation","l":"מְלֶאכֶת","s":"4399","m":"Ncfsc","tr":""},{"t":"ךָ֙","a":" ","g":"[is].your","l":"הוּא","s":"3509","m":"Sp2ms","tr":""},{"t":"וּ","a":"","g":"and","l":"וְ","s":"2050","m":"C","tr":"û"},{"t":"מֵ","a":"","g":"from","l":"מִן","s":"4480","m":"R","tr":"mē"},{"t":"אַ֣יִן","a":" ","g":"where?","l":"אַיִן","s":"370","m":"Ti","tr":"ʾayin"},{"t":"תָּב֔וֹא","a":" ","g":"do.you.come","l":"בּוֹא","s":"935","m":"Vqi2ms","tr":"tāḇôʾ"},{"t":"מָ֣ה","a":" ","g":"what?","l":"מָה","s":"4100","m":"Ti","tr":"māh"},{"t":"אַרְצֶ֔","a":"","g":"land","l":"אֶרֶץ","s":"776","m":"Ncbsc","tr":""},{"t":"ךָ","a":" ","g":"[is].your","l":"הוּא","s":"3509","m":"Sp2ms","tr":""},{"t":"וְ","a":"","g":"and","l":"וְ","s":"2050","m":"C","tr":"wə"},{"t":"אֵֽי","a":"־","g":"where?","l":"אַי","s":"335","m":"Ti","tr":"ʾēy-"},{"t":"מִ","a":"","g":"from","l":"מִן","s":"4480","m":"R","tr":"mi"},{"t":"זֶּ֥ה","a":" ","g":"this","l":"זֶה","s":"2088","m":"Pdxms","tr":"zzeh"},{"t":"עַ֖ם","a":" ","g":"people","l":"עַם","s":"5971","m":"Ncmsa","tr":"ʿam"},{"t":"אָֽתָּה","a":"׃","g":"[are].you","l":"אַתָּה","s":"859","m":"Pp2ms","tr":"ʾātâ:"}],"1:9":[{"t":"וַ","a":"","g":"and","l":"וְ","s":"2050","m":"C","tr":"wa"},{"t":"יֹּ֥אמֶר","a":" ","g":"he.said","l":"אָמַר","s":"559","m":"Vqw3ms","tr":"yyōʾmer"},{"t":"אֲלֵי","a":"","g":"to","l":"אֶל","s":"413","m":"R","tr":""},{"t":"הֶ֖ם","a":" ","g":"them","l":"הוּא","s":"3963","m":"Sp3mp","tr":""},{"t":"עִבְרִ֣י","a":" ","g":"[am].a.Hebrew","l":"עִבְרִי","s":"5680","m":"Ngmsa","tr":"ʿiḇriy"},{"t":"אָנֹ֑כִי","a":" ","g":"I","l":"אָנֹכִי","s":"595","m":"Pp1cs","tr":"ʾānōḵî"},{"t":"וְ","a":"","g":"and","l":"וְ","s":"2050","m":"C","tr":"wə"},{"t":"אֶת","a":"־","g":"(et)","l":"אֵת","s":"853","m":"To","tr":"ʾeṯ-"},{"t":"יְהוָ֞ה","a":" ","g":"Yahweh","l":"יהוה","s":"3068","m":"Np","tr":"yəhwāh"},{"t":"אֱלֹהֵ֤י","a":" ","g":"the.God","l":"אֱלֹהִים","s":"430","m":"Ncmpc","tr":"ʾĕlōhēy"},{"t":"הַ","a":"","g":"of","l":"הַ","s":"1886","m":"Td","tr":"ha"},{"t":"שָּׁמַ֨יִם֙","a":" ","g":"the.heavens","l":"שָׁמַיִם","s":"8064","m":"Ncmpa","tr":"ššāmayim"},{"t":"אֲנִ֣י","a":" ","g":"I","l":"אֲנִי","s":"589","m":"Pp1cs","tr":"ʾăniy"},{"t":"יָרֵ֔א","a":" ","g":"[am].fearing","l":"יָרֵא","s":"3373","m":"Vqp3ms","tr":"yārēʾ"},{"t":"אֲשֶׁר","a":"־","g":"who","l":"אֲשֶׁר","s":"834","m":"Tr","tr":"ʾăšer-"},{"t":"עָשָׂ֥ה","a":" ","g":"he.made","l":"עָשָׂה","s":"6213","m":"Vqp3ms","tr":"ʿāśāh"},{"t":"אֶת","a":"־","g":"(et)","l":"אֵת","s":"853","m":"To","tr":"ʾeṯ-"},{"t":"הַ","a":"","g":"the","l":"הַ","s":"1886","m":"Td","tr":"ha"},{"t":"יָּ֖ם","a":" ","g":"sea","l":"יָם","s":"3220","m":"Ncmsa","tr":"yyām"},{"t":"וְ","a":"","g":"and","l":"וְ","s":"2050","m":"C","tr":"wə"},{"t":"אֶת","a":"־","g":"(et)","l":"אֵת","s":"853","m":"To","tr":"ʾeṯ-"},{"t":"הַ","a":"","g":"the.dry","l":"הַ","s":"1886","m":"Td","tr":"ha"},{"t":"יַּבָּשָֽׁה","a":"׃","g":"land","l":"יַבָּשָׁה","s":"3004","m":"Ncfsa","tr":"yyabbāšāh:"}],"1:10":[{"t":"וַ","a":"","g":"and","l":"וְ","s":"2050","m":"C","tr":"wa"},{"t":"יִּֽירְא֤וּ","a":" ","g":"they.feared","l":"יָרֵא","s":"3372","m":"Vqw3mp","tr":"yyiyrəʾû"},{"t":"הָֽ","a":"","g":"the","l":"הַ","s":"1886","m":"Td","tr":"hā"},{"t":"אֲנָשִׁים֙","a":" ","g":"men","l":"אִישׁ","s":"376","m":"Ncmpa","tr":"ʾănāšîm"},{"t":"יִרְאָ֣ה","a":" ","g":"a.fear","l":"יִרְאָה","s":"3374","m":"Ncfsa","tr":"yirʾāh"},{"t":"גְדוֹלָ֔ה","a":" ","g":"great","l":"גָּדוֹל","s":"1419","m":"Aafsa","tr":"ḡəḏôlāh"},{"t":"וַ","a":"","g":"and","l":"וְ","s":"2050","m":"C","tr":"wa"},{"t":"יֹּאמְר֥וּ","a":" ","g":"they.said","l":"אָמַר","s":"559","m":"Vqw3mp","tr":"yyōʾmərû"},{"t":"אֵלָ֖י","a":"","g":"to","l":"אֶל","s":"413","m":"R","tr":""},{"t":"ו","a":" ","g":"him","l":"הוּא","s":"2050","m":"Sp3ms","tr":""},{"t":"מַה","a":"־","g":"what?","l":"מָה","s":"4100","m":"Ti","tr":"mah-"},{"t":"זֹּ֣את","a":" ","g":"this","l":"זֹאת","s":"2063","m":"Pdxfs","tr":"zzōʾṯ"},{"t":"עָשִׂ֑יתָ","a":" ","g":"have.you.done","l":"עָשָׂה","s":"6213","m":"Vqp2ms","tr":"ʿāśiyṯā"},{"t":"כִּֽי","a":"־","g":"(dm)","l":"כִּי","s":"3588","m":"C","tr":"kiy-"},{"t":"יָדְע֣וּ","a":" ","g":"they.knew","l":"יָדַע","s":"3045","m":"Vqp3cp","tr":"yāḏʿû"},{"t":"הָ","a":"","g":"the","l":"הַ","s":"1886","m":"Td","tr":"hā"},{"t":"אֲנָשִׁ֗ים","a":" ","g":"men","l":"אִישׁ","s":"376","m":"Ncmpa","tr":"ʾănāšiym"},{"t":"כִּֽי","a":"־","g":"(dm).that","l":"כִּי","s":"3588","m":"C","tr":"kiy-"},{"t":"מִ","a":"","g":"from","l":"מִן","s":"4480","m":"R","tr":"mi"},{"t":"לִּ","a":"","g":"","l":"לְ","s":"3807","m":"R","tr":"lli"},{"t":"פְנֵ֤י","a":" ","g":"before","l":"פָּנֶה","s":"6440","m":"Ncbpc","tr":"p̄ənēy"},{"t":"יְהוָה֙","a":" ","g":"Yahweh","l":"יהוה","s":"3068","m":"Np","tr":"yhwh"},{"t":"ה֣וּא","a":" ","g":"he","l":"הוּא","s":"1931","m":"Pp3ms","tr":"hûʾ"},{"t":"בֹרֵ֔חַ","a":" ","g":"[was].fleeing","l":"בָּרַח","s":"1272","m":"Vqrmsa","tr":"ḇōrēᵃḥ"},{"t":"כִּ֥י","a":" ","g":"(dm)","l":"כִּי","s":"3588","m":"C","tr":"kiy"},{"t":"הִגִּ֖יד","a":" ","g":"he.had.told","l":"נָגַד","s":"5046","m":"Vhp3ms","tr":"higgiyḏ"},{"t":"לָ","a":"","g":"to","l":"לְ","s":"3807","m":"R","tr":""},{"t":"הֶֽם","a":"׃","g":"them","l":"הוּא","s":"3963","m":"Sp3mp","tr":""}],"1:11":[{"t":"וַ","a":"","g":"and","l":"וְ","s":"2050","m":"C","tr":"wa"},{"t":"יֹּאמְר֤וּ","a":" ","g":"they.said","l":"אָמַר","s":"559","m":"Vqw3mp","tr":"yyōʾmərû"},{"t":"אֵלָי","a":"","g":"to","l":"אֶל","s":"413","m":"R","tr":""},{"t":"ו֙","a":" ","g":"him","l":"הוּא","s":"2050","m":"Sp3ms","tr":""},{"t":"מַה","a":"־","g":"what?","l":"מָה","s":"4100","m":"Ti","tr":"mah-"},{"t":"נַּ֣עֲשֶׂה","a":" ","g":"will.we.do","l":"עָשָׂה","s":"6213","m":"Vqi1cp","tr":"nnaʿăśeh"},{"t":"לָּ֔","a":"","g":"to","l":"לְ","s":"3807","m":"R","tr":""},{"t":"ךְ","a":" ","g":"you","l":"הוּא","s":"3509","m":"Sp2fs","tr":""},{"t":"וְ","a":"","g":"so","l":"וְ","s":"2050","m":"C","tr":"wə"},{"t":"יִשְׁתֹּ֥ק","a":" ","g":"that.it.will.be.quiet","l":"שָׁתַק","s":"8367","m":"Vqi3ms","tr":"yištōq"},{"t":"הַ","a":"","g":"the","l":"הַ","s":"1886","m":"Td","tr":"ha"},{"t":"יָּ֖ם","a":" ","g":"sea","l":"יָם","s":"3220","m":"Ncmsa","tr":"yyām"},{"t":"מֵֽ","a":"","g":"from","l":"מִן","s":"4480","m":"R","tr":"mē"},{"t":"עָלֵ֑י","a":"","g":"on","l":"עַל","s":"5921","m":"R","tr":""},{"t":"נוּ","a":" ","g":"us","l":"הוּא","s":"5105","m":"Sp1cp","tr":""},{"t":"כִּ֥י","a":" ","g":"(dm)","l":"כִּי","s":"3588","m":"C","tr":"kiy"},{"t":"הַ","a":"","g":"the","l":"הַ","s":"1886","m":"Td","tr":"ha"},{"t":"יָּ֖ם","a":" ","g":"sea","l":"יָם","s":"3220","m":"Ncmsa","tr":"yyām"},{"t":"הוֹלֵ֥ךְ","a":" ","g":"[was].going","l":"הָלַךְ","s":"1980","m":"Vqrmsa","tr":"hôlēḵ"},{"t":"וְ","a":"","g":"and","l":"וְ","s":"2050","m":"C","tr":"wə"},{"t":"סֹעֵֽר","a":"׃","g":"storming","l":"סָעַר","s":"5590","m":"Vqrmsa","tr":"sōʿēr:"}],"1:12":[{"t":"וַ","a":"","g":"and","l":"וְ","s":"2050","m":"C","tr":"wa"},{"t":"יֹּ֣אמֶר","a":" ","g":"he.said","l":"אָמַר","s":"559","m":"Vqw3ms","tr":"yyōʾmer"},{"t":"אֲלֵי","a":"","g":"to","l":"אֶל","s":"413","m":"R","tr":""},{"t":"הֶ֗ם","a":" ","g":"them","l":"הוּא","s":"3963","m":"Sp3mp","tr":""},{"t":"שָׂא֨וּ","a":"","g":"pick","l":"נָשָׂא","s":"5375","m":"Vqv2mp","tr":""},{"t":"נִי֙","a":" ","g":"me.up","l":"הוּא","s":"5204","m":"Sp1cs","tr":""},{"t":"וַ","a":"","g":"and","l":"וְ","s":"2050","m":"C","tr":"wa"},{"t":"הֲטִילֻ֣","a":"","g":"hurl","l":"טוּל","s":"2904","m":"Vhv2mp","tr":""},{"t":"נִי","a":" ","g":"me","l":"הוּא","s":"5204","m":"Sp1cs","tr":""},{"t":"אֶל","a":"־","g":"into","l":"אֶל","s":"413","m":"R","tr":"ʾel-"},{"t":"הַ","a":"","g":"the","l":"הַ","s":"1886","m":"Td","tr":"ha"},{"t":"יָּ֔ם","a":" ","g":"sea","l":"יָם","s":"3220","m":"Ncmsa","tr":"yyām"},{"t":"וְ","a":"","g":"and","l":"וְ","s":"2050","m":"C","tr":"wə"},{"t":"יִשְׁתֹּ֥ק","a":" ","g":"it.will.be.quiet","l":"שָׁתַק","s":"8367","m":"Vqi3ms","tr":"yištōq"},{"t":"הַ","a":"","g":"the","l":"הַ","s":"1886","m":"Td","tr":"ha"},{"t":"יָּ֖ם","a":" ","g":"sea","l":"יָם","s":"3220","m":"Ncmsa","tr":"yyām"},{"t":"מֵֽ","a":"","g":"from","l":"מִן","s":"4480","m":"R","tr":"mē"},{"t":"עֲלֵי","a":"","g":"on","l":"עַל","s":"5921","m":"R","tr":""},{"t":"כֶ֑ם","a":" ","g":"you","l":"הוּא","s":"3641","m":"Sp2mp","tr":""},{"t":"כִּ֚י","a":" ","g":"(dm)","l":"כִּי","s":"3588","m":"C","tr":"kî"},{"t":"יוֹדֵ֣עַ","a":" ","g":"[am].knowing","l":"יָדַע","s":"3045","m":"Vqrmsa","tr":"yôḏēᵃʿ"},{"t":"אָ֔נִי","a":" ","g":"I","l":"אֲנִי","s":"589","m":"Pp1cs","tr":"ʾānî"},{"t":"כִּ֣י","a":" ","g":"(dm).that","l":"כִּי","s":"3588","m":"C","tr":"kiy"},{"t":"בְ","a":"","g":"by","l":"בְּ","s":"871","m":"R","tr":"ḇə"},{"t":"שֶׁ","a":"","g":"which","l":"שֶׁ","s":"7578","m":"Tr","tr":"še"},{"t":"לִּ֔","a":"","g":"of","l":"לְ","s":"3807","m":"R","tr":""},{"t":"י","a":" ","g":"me","l":"שֶׁל","s":"2967","m":"Sp1cs","tr":""},{"t":"הַ","a":"","g":"the","l":"הַ","s":"1886","m":"Td","tr":"ha"},{"t":"סַּ֧עַר","a":" ","g":"storm","l":"סַעַר","s":"5591","m":"Ncmsa","tr":"ssaʿar"},{"t":"הַ","a":"","g":"(the)","l":"הַ","s":"1886","m":"Td","tr":"ha"},{"t":"גָּד֛וֹל","a":" ","g":"great","l":"גָּדוֹל","s":"1419","m":"Aamsa","tr":"gāḏôl"},{"t":"הַ","a":"","g":"(the)","l":"הַ","s":"1886","m":"Td","tr":"ha"},{"t":"זֶּ֖ה","a":" ","g":"this","l":"זֶה","s":"2088","m":"Pdxms","tr":"zzeh"},{"t":"עֲלֵי","a":"","g":"[is].on","l":"עַל","s":"5921","m":"R","tr":""},{"t":"כֶֽם","a":"׃","g":"you","l":"הוּא","s":"3641","m":"Sp2mp","tr":""}],"1:13":[{"t":"וַ","a":"","g":"and","l":"וְ","s":"2050","m":"C","tr":"wa"},{"t":"יַּחְתְּר֣וּ","a":" ","g":"they.rowed","l":"חָתַר","s":"2864","m":"Vqw3mp","tr":"yyaḥtərû"},{"t":"הָ","a":"","g":"the","l":"הַ","s":"1886","m":"Td","tr":"hā"},{"t":"אֲנָשִׁ֗ים","a":" ","g":"men","l":"אִישׁ","s":"376","m":"Ncmpa","tr":"ʾănāšiym"},{"t":"לְ","a":"","g":"to","l":"לְ","s":"3807","m":"R","tr":"lə"},{"t":"הָשִׁ֛יב","a":" ","g":"bring.back","l":"שׁוּב","s":"7725","m":"Vhc","tr":"hāšiyḇ"},{"t":"אֶל","a":"־","g":"to","l":"אֶל","s":"413","m":"R","tr":"ʾel-"},{"t":"הַ","a":"","g":"the.dry","l":"הַ","s":"1886","m":"Td","tr":"ha"},{"t":"יַּבָּשָׁ֖ה","a":" ","g":"land","l":"יַבָּשָׁה","s":"3004","m":"Ncfsa","tr":"yyabbāšāh"},{"t":"וְ","a":"","g":"and","l":"וְ","s":"2050","m":"C","tr":"wə"},{"t":"לֹ֣א","a":" ","g":"not","l":"לֹא","s":"3808","m":"Tn","tr":"lōʾ"},{"t":"יָכֹ֑לוּ","a":" ","g":"they.were.able","l":"יָכֹל","s":"3201","m":"Vqp3cp","tr":"yāḵōlû"},{"t":"כִּ֣י","a":" ","g":"(dm)","l":"כִּי","s":"3588","m":"C","tr":"kiy"},{"t":"הַ","a":"","g":"the","l":"הַ","s":"1886","m":"Td","tr":"ha"},{"t":"יָּ֔ם","a":" ","g":"sea","l":"יָם","s":"3220","m":"Ncmsa","tr":"yyām"},{"t":"הוֹלֵ֥ךְ","a":" ","g":"[was].going","l":"הָלַךְ","s":"1980","m":"Vqrmsa","tr":"hôlēḵ"},{"t":"וְ","a":"","g":"and","l":"וְ","s":"2050","m":"C","tr":"wə"},{"t":"סֹעֵ֖ר","a":" ","g":"storming","l":"סָעַר","s":"5590","m":"Vqrmsa","tr":"sōʿēr"},{"t":"עֲלֵי","a":"","g":"on","l":"עַל","s":"5921","m":"R","tr":""},{"t":"הֶֽם","a":"׃","g":"them","l":"הוּא","s":"3963","m":"Sp3mp","tr":""}],"1:14":[{"t":"וַ","a":"","g":"and","l":"וְ","s":"2050","m":"C","tr":"wa"},{"t":"יִּקְרְא֨וּ","a":" ","g":"they.called.out","l":"קָרָא","s":"7121","m":"Vqw3mp","tr":"yyiqrəʾû"},{"t":"אֶל","a":"־","g":"to","l":"אֶל","s":"413","m":"R","tr":"ʾel-"},{"t":"יְהוָ֜ה","a":" ","g":"Yahweh","l":"יהוה","s":"3068","m":"Np","tr":"yəhwāh"},{"t":"וַ","a":"","g":"and","l":"וְ","s":"2050","m":"C","tr":"wa"},{"t":"יֹּאמְר֗וּ","a":" ","g":"they.said","l":"אָמַר","s":"559","m":"Vqw3mp","tr":"yyōʾmərû"},{"t":"אָנָּ֤ה","a":" ","g":"please!","l":"אָנָּא","s":"577","m":"Tj","tr":"ʾonnāh"},{"t":"יְהוָה֙","a":" ","g":"O.Yahweh","l":"יהוה","s":"3068","m":"Np","tr":"yhwh"},{"t":"אַל","a":"־","g":"do.not","l":"אַל","s":"408","m":"Tn","tr":"ʾal-"},{"t":"נָ֣א","a":" ","g":"please","l":"נָא","s":"4994","m":"Te","tr":"nāʾ"},{"t":"נֹאבְדָ֗ה","a":" ","g":"let.us.perish","l":"אָבַד","s":"6","m":"Vqh1cp","tr":"nōʾḇəḏāh"},{"t":"בְּ","a":"","g":"by","l":"בְּ","s":"871","m":"R","tr":"bə"},{"t":"נֶ֨פֶשׁ֙","a":" ","g":"the.life","l":"נֶפֶשׁ","s":"5315","m":"Ncbsc","tr":"nep̄eš"},{"t":"הָ","a":"","g":"of","l":"הַ","s":"1886","m":"Td","tr":"hā"},{"t":"אִ֣ישׁ","a":" ","g":"the.man","l":"אִישׁ","s":"376","m":"Ncmsa","tr":"ʾiyš"},{"t":"הַ","a":"","g":"(the)","l":"הַ","s":"1886","m":"Td","tr":"ha"},{"t":"זֶּ֔ה","a":" ","g":"this","l":"זֶה","s":"2088","m":"Pdxms","tr":"zzeh"},{"t":"וְ","a":"","g":"and","l":"וְ","s":"2050","m":"C","tr":"wə"},{"t":"אַל","a":"־","g":"do.not","l":"אַל","s":"408","m":"Tn","tr":"ʾal-"},{"t":"תִּתֵּ֥ן","a":" ","g":"put","l":"נָתַן","s":"5414","m":"Vqj2ms","tr":"tittēn"},{"t":"עָלֵ֖י","a":"","g":"on","l":"עַל","s":"5921","m":"R","tr":""},{"t":"נוּ","a":" ","g":"us","l":"הוּא","s":"5105","m":"Sp1cp","tr":""},{"t":"דָּ֣ם","a":" ","g":"blood","l":"דָּם","s":"1818","m":"Ncmsa","tr":"dām"},{"t":"נָקִ֑יא","a":" ","g":"innocent","l":"נָקִי","s":"5355","m":"Aamsa","tr":"nāqiyʾ"},{"t":"כִּֽי","a":"־","g":"(dm)","l":"כִּי","s":"3588","m":"C","tr":"kiy-"},{"t":"אַתָּ֣ה","a":" ","g":"you","l":"אַתָּה","s":"859","m":"Pp2ms","tr":"ʾattāh"},{"t":"יְהוָ֔ה","a":" ","g":"O.Yahweh","l":"יהוה","s":"3068","m":"Np","tr":"yəhwāh"},{"t":"כַּ","a":"","g":"just","l":"כְּ","s":"3509","m":"R","tr":"ka"},{"t":"אֲשֶׁ֥ר","a":" ","g":"as","l":"אֲשֶׁר","s":"834","m":"Tr","tr":"ʾăšer"},{"t":"חָפַ֖צְתָּ","a":" ","g":"you.pleased","l":"חָפֵץ","s":"2654","m":"Vqp2ms","tr":"ḥāp̄aṣətā"},{"t":"עָשִֽׂיתָ","a":"׃","g":"you.have.done","l":"עָשָׂה","s":"6213","m":"Vqp2ms","tr":"ʿāśiyṯā:"}],"1:15":[{"t":"וַ","a":"","g":"and","l":"וְ","s":"2050","m":"C","tr":"wa"},{"t":"יִּשְׂאוּ֙","a":" ","g":"they.picked.up","l":"נָשָׂא","s":"5375","m":"Vqw3mp","tr":"yyiśʾû"},{"t":"אֶת","a":"־","g":"(et)","l":"אֵת","s":"853","m":"To","tr":"ʾeṯ-"},{"t":"יוֹנָ֔ה","a":" ","g":"Jonah","l":"יוֹנָה","s":"3124","m":"Np","tr":"yônāh"},{"t":"וַ","a":"","g":"and","l":"וְ","s":"2050","m":"C","tr":"wa"},{"t":"יְטִלֻ֖","a":"","g":"they","l":"טוּל","s":"2904","m":"Vhw3mp","tr":""},{"t":"הוּ","a":" ","g":"hurled.him","l":"הוּא","s":"1930","m":"Sp3ms","tr":""},{"t":"אֶל","a":"־","g":"into","l":"אֶל","s":"413","m":"R","tr":"ʾel-"},{"t":"הַ","a":"","g":"the","l":"הַ","s":"1886","m":"Td","tr":"ha"},{"t":"יָּ֑ם","a":" ","g":"sea","l":"יָם","s":"3220","m":"Ncmsa","tr":"yyām"},{"t":"וַ","a":"","g":"and","l":"וְ","s":"2050","m":"C","tr":"wa"},{"t":"יַּעֲמֹ֥ד","a":" ","g":"it.stopped","l":"עָמַד","s":"5975","m":"Vqw3ms","tr":"yyaʿămōḏ"},{"t":"הַ","a":"","g":"the","l":"הַ","s":"1886","m":"Td","tr":"ha"},{"t":"יָּ֖ם","a":" ","g":"sea","l":"יָם","s":"3220","m":"Ncmsa","tr":"yyām"},{"t":"מִ","a":"","g":"from","l":"מִן","s":"4480","m":"R","tr":"mi"},{"t":"זַּעְפּֽ","a":"","g":"storming","l":"זַעַף","s":"2196","m":"Vqc","tr":""},{"t":"וֹ","a":"׃","g":"its","l":"הוּא","s":"2050","m":"Sp3ms","tr":""}],"1:16":[{"t":"וַ","a":"","g":"and","l":"וְ","s":"2050","m":"C","tr":"wa"},{"t":"יִּֽירְא֧וּ","a":" ","g":"they.feared","l":"יָרֵא","s":"3372","m":"Vqw3mp","tr":"yyiyrəʾû"},{"t":"הָ","a":"","g":"the","l":"הַ","s":"1886","m":"Td","tr":"hā"},{"t":"אֲנָשִׁ֛ים","a":" ","g":"men","l":"אִישׁ","s":"376","m":"Ncmpa","tr":"ʾănāšiym"},{"t":"יִרְאָ֥ה","a":" ","g":"a.fear","l":"יִרְאָה","s":"3374","m":"Ncfsa","tr":"yirʾāh"},{"t":"גְדוֹלָ֖ה","a":" ","g":"great","l":"גָּדוֹל","s":"1419","m":"Aafsa","tr":"ḡəḏôlāh"},{"t":"אֶת","a":"־","g":"(et)","l":"אֵת","s":"853","m":"To","tr":"ʾeṯ-"},{"t":"יְהוָ֑ה","a":" ","g":"Yahweh","l":"יהוה","s":"3068","m":"Np","tr":"yəhwāh"},{"t":"וַ","a":"","g":"and","l":"וְ","s":"2050","m":"C","tr":"wa"},{"t":"יִּֽזְבְּחוּ","a":"־","g":"they.sacrificed","l":"זָבַח","s":"2076","m":"Vqw3mp","tr":"yyizbəḥû-"},{"t":"זֶ֨בַח֙","a":" ","g":"a.sacrifice","l":"זֶבַח","s":"2077","m":"Ncmsa","tr":"zeḇaḥ"},{"t":"לַֽ","a":"","g":"to","l":"לְ","s":"3807","m":"R","tr":"la"},{"t":"יהוָ֔ה","a":" ","g":"Yahweh","l":"יהוה","s":"3068","m":"Np","tr":"yhwāh"},{"t":"וַֽ","a":"","g":"and","l":"וְ","s":"2050","m":"C","tr":"wa"},{"t":"יִּדְּר֖וּ","a":" ","g":"they.vowed","l":"נָדַר","s":"5087","m":"Vqw3mp","tr":"yyiddərû"},{"t":"נְדָרִֽים","a":"׃","g":"vows","l":"נֶדֶר","s":"5088","m":"Ncmpa","tr":"nəḏāriym:"}],"2:1":[{"t":"וַ","a":"","g":"and","l":"וְ","s":"2050","m":"C","tr":"wa"},{"t":"יְמַ֤ן","a":" ","g":"he.appointed","l":"מָנָה","s":"4487","m":"Vpw3ms","tr":"yəman"},{"t":"יְהוָה֙","a":" ","g":"Yahweh","l":"יהוה","s":"3068","m":"Np","tr":"yhwh"},{"t":"דָּ֣ג","a":" ","g":"a.fish","l":"דָּג","s":"1709","m":"Ncmsa","tr":"dāḡ"},{"t":"גָּד֔וֹל","a":" ","g":"great","l":"גָּדוֹל","s":"1419","m":"Aamsa","tr":"gāḏôl"},{"t":"לִ","a":"","g":"to","l":"לְ","s":"3807","m":"R","tr":"li"},{"t":"בְלֹ֖עַ","a":" ","g":"swallow","l":"בָּלַע","s":"1104","m":"Vqc","tr":"ḇəlōᵃʿ"},{"t":"אֶת","a":"־","g":"(et)","l":"אֵת","s":"853","m":"To","tr":"ʾeṯ-"},{"t":"יוֹנָ֑ה","a":" ","g":"Jonah","l":"יוֹנָה","s":"3124","m":"Np","tr":"yônāh"},{"t":"וַ","a":"","g":"and","l":"וְ","s":"2050","m":"C","tr":"wa"},{"t":"יְהִ֤י","a":" ","g":"he.was","l":"הָיָה","s":"1961","m":"Vqw3ms","tr":"yəhiy"},{"t":"יוֹנָה֙","a":" ","g":"Jonah","l":"יוֹנָה","s":"3124","m":"Np","tr":"yônāh"},{"t":"בִּ","a":"","g":"in","l":"בְּ","s":"871","m":"R","tr":"bi"},{"t":"מְעֵ֣י","a":" ","g":"the.inward.parts","l":"מֵעִים","s":"4578","m":"Ncmpc","tr":"məʿēy"},{"t":"הַ","a":"","g":"of","l":"הַ","s":"1886","m":"Td","tr":"ha"},{"t":"דָּ֔ג","a":" ","g":"the.fish","l":"דָּג","s":"1709","m":"Ncmsa","tr":"dāḡ"},{"t":"שְׁלֹשָׁ֥ה","a":" ","g":"three","l":"שָׁלֹשׁ","s":"7969","m":"Acmsa","tr":"šəlōšāh"},{"t":"יָמִ֖ים","a":" ","g":"days","l":"יוֹם","s":"3117","m":"Ncmpa","tr":"yāmiym"},{"t":"וּ","a":"","g":"and","l":"וְ","s":"2050","m":"C","tr":"û"},{"t":"שְׁלֹשָׁ֥ה","a":" ","g":"three","l":"שָׁלֹשׁ","s":"7969","m":"Acmsa","tr":"šəlōšāh"},{"t":"לֵילֽוֹת","a":"׃","g":"nights","l":"לַיְלָה","s":"3915","m":"Ncmpa","tr":"lêlôṯ:"}],"2:2":[{"t":"וַ","a":"","g":"and","l":"וְ","s":"2050","m":"C","tr":"wa"},{"t":"יִּתְפַּלֵּ֣ל","a":" ","g":"he.prayed","l":"פָּלַל","s":"6419","m":"Vtw3ms","tr":"yyiṯpallēl"},{"t":"יוֹנָ֔ה","a":" ","g":"Jonah","l":"יוֹנָה","s":"3124","m":"Np","tr":"yônāh"},{"t":"אֶל","a":"־","g":"to","l":"אֶל","s":"413","m":"R","tr":"ʾel-"},{"t":"יְהוָ֖ה","a":" ","g":"Yahweh","l":"יהוה","s":"3068","m":"Np","tr":"yəhwāh"},{"t":"אֱלֹהָ֑י","a":"","g":"God","l":"אֱלֹהִים","s":"430","m":"Ncmpc","tr":""},{"t":"ו","a":" ","g":"his","l":"הוּא","s":"2050","m":"Sp3ms","tr":""},{"t":"מִ","a":"","g":"from","l":"מִן","s":"4480","m":"R","tr":"mi"},{"t":"מְּעֵ֖י","a":" ","g":"the.inward.parts","l":"מֵעִים","s":"4578","m":"Ncmpc","tr":"mməʿēy"},{"t":"הַ","a":"","g":"of","l":"הַ","s":"1886","m":"Td","tr":"ha"},{"t":"דָּגָֽה","a":"׃","g":"the.fish","l":"דָּגָה","s":"1710","m":"Ncfsa","tr":"dāḡāh:"}],"2:3":[{"t":"וַ","a":"","g":"and","l":"וְ","s":"2050","m":"C","tr":"wa"},{"t":"יֹּ֗אמֶר","a":" ","g":"he.said","l":"אָמַר","s":"559","m":"Vqw3ms","tr":"yyōʾmer"},{"t":"קָ֠רָאתִי","a":" ","g":"I.called","l":"קָרָא","s":"7121","m":"Vqp1cs","tr":"qārāʾṯî"},{"t":"מִ","a":"","g":"from","l":"מִן","s":"4480","m":"R","tr":"mi"},{"t":"צָּ֥רָה","a":" ","g":"distress","l":"צָרָה","s":"6869","m":"Ncfsa","tr":"ṣṣārâ"},{"t":"לִ֛","a":"","g":"of","l":"לְ","s":"3807","m":"R","tr":""},{"t":"י","a":" ","g":"my","l":"הוּא","s":"2967","m":"Sp1cs","tr":""},{"t":"אֶל","a":"־","g":"to","l":"אֶל","s":"413","m":"R","tr":"ʾel-"},{"t":"יְהוָ֖ה","a":" ","g":"Yahweh","l":"יהוה","s":"3068","m":"Np","tr":"yəhwāh"},{"t":"וַֽ","a":"","g":"and","l":"וְ","s":"2050","m":"C","tr":"wa"},{"t":"יַּעֲנֵ֑","a":"","g":"he","l":"עָנָה","s":"6030","m":"Vqw3ms","tr":""},{"t":"נִי","a":" ","g":"answered.me","l":"הוּא","s":"5204","m":"Sp1cs","tr":""},{"t":"מִ","a":"","g":"from","l":"מִן","s":"4480","m":"R","tr":"mi"},{"t":"בֶּ֧טֶן","a":" ","g":"the.belly","l":"בֶּטֶן","s":"990","m":"Ncfsc","tr":"beṭen"},{"t":"שְׁא֛וֹל","a":" ","g":"of.Sheol","l":"שְׁאוֹל","s":"7585","m":"Np","tr":"šəʾôl"},{"t":"שִׁוַּ֖עְתִּי","a":" ","g":"I.cried.for.help","l":"שָׁוַע","s":"7768","m":"Vpp1cs","tr":"šiwwaʿətî"},{"t":"שָׁמַ֥עְתָּ","a":" ","g":"you.heard","l":"שָׁמַע","s":"8085","m":"Vqp2ms","tr":"šāmaʿətā"},{"t":"קוֹלִֽ","a":"","g":"voice","l":"קוֹל","s":"6963","m":"Ncmsc","tr":""},{"t":"י","a":"׃","g":"my","l":"הוּא","s":"2967","m":"Sp1cs","tr":""}],"2:4":[{"t":"וַ","a":"","g":"and","l":"וְ","s":"2050","m":"C","tr":"wa"},{"t":"תַּשְׁלִיכֵ֤","a":"","g":"you","l":"שָׁלַךְ","s":"7993","m":"Vhw2ms","tr":""},{"t":"נִי","a":" ","g":"have.thrown.me","l":"הוּא","s":"5204","m":"Sp1cs","tr":""},{"t":"מְצוּלָה֙","a":" ","g":"[the].deep","l":"מְצוֹלָה","s":"4688","m":"Ncfsa","tr":"məṣûlāh"},{"t":"בִּ","a":"","g":"in.[the]","l":"בְּ","s":"871","m":"R","tr":"bi"},{"t":"לְבַ֣ב","a":" ","g":"heart","l":"לֵבָב","s":"3824","m":"Ncmsc","tr":"ləḇaḇ"},{"t":"יַמִּ֔ים","a":" ","g":"of.[the].seas","l":"יָם","s":"3220","m":"Ncmpa","tr":"yammiym"},{"t":"וְ","a":"","g":"and","l":"וְ","s":"2050","m":"R","tr":"wə"},{"t":"נָהָ֖ר","a":" ","g":"a.river","l":"נָהָר","s":"5104","m":"Ncmsa","tr":"nāhār"},{"t":"יְסֹבְבֵ֑","a":"","g":"it","l":"סָבַב","s":"5437","m":"Vmi3ms","tr":""},{"t":"נִי","a":" ","g":"surrounds.me","l":"הוּא","s":"5204","m":"Sp1cs","tr":""},{"t":"כָּל","a":"־","g":"all","l":"כֹּל","s":"3605","m":"Ncmsc","tr":"kol-"},{"t":"מִשְׁבָּרֶ֥י","a":"","g":"breakers","l":"מִשְׁבָּר","s":"4867","m":"Ncmpc","tr":""},{"t":"ךָ","a":" ","g":"your","l":"הוּא","s":"3509","m":"Sp2ms","tr":""},{"t":"וְ","a":"","g":"and","l":"וְ","s":"2050","m":"C","tr":"wə"},{"t":"גַלֶּ֖י","a":"","g":"waves","l":"גַּל","s":"1530","m":"Ncmpc","tr":""},{"t":"ךָ","a":" ","g":"your","l":"הוּא","s":"3509","m":"Sp2ms","tr":""},{"t":"עָלַ֥","a":"","g":"over","l":"עַל","s":"5921","m":"R","tr":""},{"t":"י","a":" ","g":"me","l":"הוּא","s":"2967","m":"Sp1cs","tr":""},{"t":"עָבָֽרוּ","a":"׃","g":"they.have.passed","l":"עָבַר","s":"5674","m":"Vqp3cp","tr":"ʿāḇārû:"}],"2:5":[{"t":"וַ","a":"","g":"and","l":"וְ","s":"2050","m":"C","tr":"wa"},{"t":"אֲנִ֣י","a":" ","g":"I","l":"אֲנִי","s":"589","m":"Pp1cs","tr":"ʾăniy"},{"t":"אָמַ֔רְתִּי","a":" ","g":"I.said","l":"אָמַר","s":"559","m":"Vqp1cs","tr":"ʾāmarətî"},{"t":"נִגְרַ֖שְׁתִּי","a":" ","g":"I.have.been.driven.away","l":"גָּרַשׁ","s":"1644","m":"VNp1cs","tr":"niḡrašətî"},{"t":"מִ","a":"","g":"from","l":"מִן","s":"4480","m":"R","tr":"mi"},{"t":"נֶּ֣גֶד","a":" ","g":"before","l":"נֶגֶד","s":"5048","m":"R","tr":"nneḡeḏ"},{"t":"עֵינֶ֑י","a":"","g":"eyes","l":"עַיִן","s":"5869","m":"Ncbdc","tr":""},{"t":"ךָ","a":" ","g":"your","l":"הוּא","s":"3509","m":"Sp2ms","tr":""},{"t":"אַ֚ךְ","a":" ","g":"nevertheless","l":"אַךְ","s":"389","m":"Ta","tr":"ʾaḵ"},{"t":"אוֹסִ֣יף","a":" ","g":"I.will.repeat","l":"יָסַף","s":"3254","m":"Vhi1cs","tr":"ʾôsiyp̄"},{"t":"לְ","a":"","g":"to","l":"לְ","s":"3807","m":"R","tr":"lə"},{"t":"הַבִּ֔יט","a":" ","g":"look","l":"נָבַט","s":"5027","m":"Vhc","tr":"habbiyṭ"},{"t":"אֶל","a":"־","g":"to","l":"אֶל","s":"413","m":"R","tr":"ʾel-"},{"t":"הֵיכַ֖ל","a":" ","g":"the.temple","l":"הֵיכָל","s":"1964","m":"Ncmsc","tr":"hêḵal"},{"t":"קָדְשֶֽׁ","a":"","g":"your.holiness","l":"קֹדֶשׁ","s":"6944","m":"Ncmsc","tr":""},{"t":"ךָ","a":"׃","g":"your","l":"הוּא","s":"3509","m":"Sp2ms","tr":""}],"2:6":[{"t":"אֲפָפ֤וּ","a":"","g":"they","l":"אָפַף","s":"661","m":"Vqp3cp","tr":""},{"t":"נִי","a":" ","g":"have.encompassed.me","l":"הוּא","s":"5204","m":"Sp1cs","tr":""},{"t":"מַ֨יִם֙","a":" ","g":"waters","l":"מַיִם","s":"4325","m":"Ncmpa","tr":"mayim"},{"t":"עַד","a":"־","g":"to","l":"עַד","s":"5704","m":"R","tr":"ʿaḏ-"},{"t":"נֶ֔פֶשׁ","a":" ","g":"[the].neck","l":"נֶפֶשׁ","s":"5315","m":"Ncbsa","tr":"nep̄eš"},{"t":"תְּה֖וֹם","a":" ","g":"the.deep","l":"תְּהוֹם","s":"8415","m":"Ncbsa","tr":"təhôm"},{"t":"יְסֹבְבֵ֑","a":"","g":"it","l":"סָבַב","s":"5437","m":"Vmi3ms","tr":""},{"t":"נִי","a":" ","g":"surrounds.me","l":"הוּא","s":"5204","m":"Sp1cs","tr":""},{"t":"ס֖וּף","a":" ","g":"rush[es]","l":"סוּף","s":"5488","m":"Ncmsa","tr":"sûp̄"},{"t":"חָב֥וּשׁ","a":" ","g":"[is].wrapped.round","l":"חָבַשׁ","s":"2280","m":"Vqsmsa","tr":"ḥāḇûš"},{"t":"לְ","a":"","g":"to","l":"לְ","s":"3807","m":"R","tr":"lə"},{"t":"רֹאשִֽׁ","a":"","g":"head","l":"רֹאשׁ","s":"7218","m":"Ncmsc","tr":""},{"t":"י","a":"׃","g":"my","l":"הוּא","s":"2967","m":"Sp1cs","tr":""}],"2:7":[{"t":"לְ","a":"","g":"to","l":"לְ","s":"3807","m":"R","tr":"lə"},{"t":"קִצְבֵ֤י","a":" ","g":"extremities","l":"קֶצֶב","s":"7095","m":"Ncmpc","tr":"qiṣḇēy"},{"t":"הָרִים֙","a":" ","g":"of.mountains","l":"הַר","s":"2022","m":"Ncmpa","tr":"hārîm"},{"t":"יָרַ֔דְתִּי","a":" ","g":"I.went.down","l":"יָרַד","s":"3381","m":"Vqp1cs","tr":"yāraḏətî"},{"t":"הָ","a":"","g":"the","l":"הַ","s":"1886","m":"Td","tr":"hā"},{"t":"אָ֛רֶץ","a":" ","g":"earth","l":"אֶרֶץ","s":"776","m":"Ncbsa","tr":"ʾāreṣ"},{"t":"בְּרִחֶ֥י","a":"","g":"bars","l":"בְּרִיחַ","s":"1280","m":"Ncmpc","tr":""},{"t":"הָ","a":" ","g":"its","l":"הוּא","s":"1886","m":"Sp3fs","tr":""},{"t":"בַעֲדִ֖","a":"","g":"[were].behind","l":"בַּעַד","s":"1157","m":"R","tr":""},{"t":"י","a":" ","g":"me","l":"הוּא","s":"2967","m":"Sp1cs","tr":""},{"t":"לְ","a":"","g":"forever","l":"לְ","s":"3807","m":"R","tr":"lə"},{"t":"עוֹלָ֑ם","a":" ","g":"of.perpetuity","l":"עוֹלָם","s":"5769","m":"Ncmsa","tr":"ʿôlām"},{"t":"וַ","a":"","g":"and","l":"וְ","s":"2050","m":"C","tr":"wa"},{"t":"תַּ֧עַל","a":" ","g":"you.brought.up","l":"עָלָה","s":"5927","m":"Vhw2ms","tr":"taʿal"},{"t":"מִ","a":"","g":"from.[the]","l":"מִן","s":"4480","m":"R","tr":"mi"},{"t":"שַּׁ֛חַת","a":" ","g":"pit","l":"שַׁחַת","s":"7845","m":"Ncfsa","tr":"ššaḥaṯ"},{"t":"חַיַּ֖","a":"","g":"life","l":"חַיִּים","s":"2416","m":"Ncmpc","tr":""},{"t":"י","a":" ","g":"my","l":"הוּא","s":"2967","m":"Sp1cs","tr":""},{"t":"יְהוָ֥ה","a":" ","g":"O.Yahweh","l":"יהוה","s":"3068","m":"Np","tr":"yəhwāh"},{"t":"אֱלֹהָֽ","a":"","g":"God","l":"אֱלֹהִים","s":"430","m":"Ncmpc","tr":""},{"t":"י","a":"׃","g":"my","l":"הוּא","s":"2967","m":"Sp1cs","tr":""}],"2:8":[{"t":"בְּ","a":"","g":"when","l":"בְּ","s":"871","m":"R","tr":"bə"},{"t":"הִתְעַטֵּ֤ף","a":" ","g":"fainted.away","l":"עָטַף","s":"5848","m":"Vtc","tr":"hiṯʿaṭṭēp̄"},{"t":"עָלַ","a":"","g":"on","l":"עַל","s":"5921","m":"R","tr":""},{"t":"י֙","a":" ","g":"me","l":"הוּא","s":"2967","m":"Sp1cs","tr":""},{"t":"נַפְשִׁ֔","a":"","g":"life","l":"נֶפֶשׁ","s":"5315","m":"Ncbsc","tr":""},{"t":"י","a":" ","g":"my","l":"הוּא","s":"2967","m":"Sp1cs","tr":""},{"t":"אֶת","a":"־","g":"(et)","l":"אֵת","s":"853","m":"To","tr":"ʾeṯ-"},{"t":"יְהוָ֖ה","a":" ","g":"Yahweh","l":"יהוה","s":"3068","m":"Np","tr":"yəhwāh"},{"t":"זָכָ֑רְתִּי","a":" ","g":"I.remembered","l":"זָכַר","s":"2142","m":"Vqp1cs","tr":"zāḵārətî"},{"t":"וַ","a":"","g":"and","l":"וְ","s":"2050","m":"C","tr":"wa"},{"t":"תָּב֤וֹא","a":" ","g":"it.came","l":"בּוֹא","s":"935","m":"Vqw3fs","tr":"tāḇôʾ"},{"t":"אֵלֶ֨י","a":"","g":"to","l":"אֶל","s":"413","m":"R","tr":""},{"t":"ךָ֙","a":" ","g":"you","l":"הוּא","s":"3509","m":"Sp2ms","tr":""},{"t":"תְּפִלָּתִ֔","a":"","g":"prayer","l":"תְּפִלָּה","s":"8605","m":"Ncfsc","tr":""},{"t":"י","a":" ","g":"my","l":"הוּא","s":"2967","m":"Sp1cs","tr":""},{"t":"אֶל","a":"־","g":"to","l":"אֶל","s":"413","m":"R","tr":"ʾel-"},{"t":"הֵיכַ֖ל","a":" ","g":"the.temple","l":"הֵיכָל","s":"1964","m":"Ncmsc","tr":"hêḵal"},{"t":"קָדְשֶֽׁ","a":"","g":"your.holiness","l":"קֹדֶשׁ","s":"6944","m":"Ncmsc","tr":""},{"t":"ךָ","a":"׃","g":"your","l":"הוּא","s":"3509","m":"Sp2ms","tr":""}],"2:9":[{"t":"מְשַׁמְּרִ֖ים","a":" ","g":"[those.who].pay.regard","l":"שָׁמַר","s":"8104","m":"Vprmpa","tr":"məšamməriym"},{"t":"הַבְלֵי","a":"־","g":"vanities","l":"הֶבֶל","s":"1892","m":"Ncmpc","tr":"haḇlê-"},{"t":"שָׁ֑וְא","a":" ","g":"of.nothingness","l":"שָׁוְא","s":"7723","m":"Ncmsa","tr":"šāwəʾ"},{"t":"חַסְדָּ֖","a":"","g":"loyalty","l":"חֶסֶד","s":"2617","m":"Ncmsc","tr":""},{"t":"ם","a":" ","g":"their","l":"הוּא","s":"3963","m":"Sp3mp","tr":""},{"t":"יַעֲזֹֽבוּ","a":"׃","g":"they.abandon","l":"עָזַב","s":"5800","m":"Vqi3mp","tr":"yaʿăzōḇû:"}],"2:10":[{"t":"וַ","a":"","g":"and","l":"וְ","s":"2050","m":"C","tr":"wa"},{"t":"אֲנִ֗י","a":" ","g":"I","l":"אֲנִי","s":"589","m":"Pp1cs","tr":"ʾăniy"},{"t":"בְּ","a":"","g":"with","l":"בְּ","s":"871","m":"R","tr":"bə"},{"t":"ק֤וֹל","a":" ","g":"a.voice","l":"קוֹל","s":"6963","m":"Ncmsc","tr":"qôl"},{"t":"תּוֹדָה֙","a":" ","g":"of.thanksgiving","l":"תּוֹדָה","s":"8426","m":"Ncfsa","tr":"tôḏāh"},{"t":"אֶזְבְּחָה","a":"־","g":"I.will.sacrifice","l":"זָבַח","s":"2076","m":"Vqh1cs","tr":"ʾezbəḥâ-"},{"t":"לָּ֔","a":"","g":"to","l":"לְ","s":"3807","m":"R","tr":""},{"t":"ךְ","a":" ","g":"you","l":"הוּא","s":"3509","m":"Sp2fs","tr":""},{"t":"אֲשֶׁ֥ר","a":" ","g":"[that].which","l":"אֲשֶׁר","s":"834","m":"Tr","tr":"ʾăšer"},{"t":"נָדַ֖רְתִּי","a":" ","g":"I.have.vowed","l":"נָדַר","s":"5087","m":"Vqp1cs","tr":"nāḏarətî"},{"t":"אֲשַׁלֵּ֑מָה","a":" ","g":"I.will.fulfill","l":"שָׁלֵם","s":"7999","m":"Vph1cs","tr":"ʾăšallēmâ"},{"t":"יְשׁוּעָ֖תָ","a":"","g":"rescue","l":"יְשׁוּעָה","s":"3444","m":"Ncfsa","tr":""},{"t":"ה","a":" ","g":"","l":"ה","s":"1886","m":"Sh","tr":""},{"t":"לַ","a":"","g":"[belongs].to","l":"לְ","s":"3807","m":"R","tr":"la"},{"t":"יהוָֽה","a":"׃ס","g":"Yahweh","l":"יהוה","s":"3068","m":"Np","tr":"yhwāh:"}],"2:11":[{"t":"וַ","a":"","g":"and","l":"וְ","s":"2050","m":"C","tr":"wa"},{"t":"יֹּ֥אמֶר","a":" ","g":"he.spoke","l":"אָמַר","s":"559","m":"Vqw3ms","tr":"yyōʾmer"},{"t":"יְהוָ֖ה","a":" ","g":"Yahweh","l":"יהוה","s":"3068","m":"Np","tr":"yəhwāh"},{"t":"לַ","a":"","g":"to","l":"לְ","s":"3807","m":"Rd","tr":"la"},{"t":"","a":"","g":"the","l":"הַ","s":"1886","m":"Td","tr":"–"},{"t":"דָּ֑ג","a":" ","g":"fish","l":"דָּג","s":"1709","m":"Ncmsa","tr":"dāḡ"},{"t":"וַ","a":"","g":"and","l":"וְ","s":"2050","m":"C","tr":"wa"},{"t":"יָּקֵ֥א","a":" ","g":"it.vomited.up","l":"קִיא","s":"7006","m":"Vhw3ms","tr":"yyāqēʾ"},{"t":"אֶת","a":"־","g":"(et)","l":"אֵת","s":"853","m":"To","tr":"ʾeṯ-"},{"t":"יוֹנָ֖ה","a":" ","g":"Jonah","l":"יוֹנָה","s":"3124","m":"Np","tr":"yônāh"},{"t":"אֶל","a":"־","g":"to","l":"אֶל","s":"413","m":"R","tr":"ʾel-"},{"t":"הַ","a":"","g":"the.dry","l":"הַ","s":"1886","m":"Td","tr":"ha"},{"t":"יַּבָּשָֽׁה","a":"׃פ","g":"land","l":"יַבָּשָׁה","s":"3004","m":"Ncfsa","tr":"yyabbāšāh:"}],"3:1":[{"t":"וַ","a":"","g":"and","l":"וְ","s":"2050","m":"C","tr":"wa"},{"t":"יְהִ֧י","a":" ","g":"it.came","l":"הָיָה","s":"1961","m":"Vqw3ms","tr":"yəhiy"},{"t":"דְבַר","a":"־","g":"the.word","l":"דָּבָר","s":"1697","m":"Ncmsc","tr":"ḏəḇar-"},{"t":"יְהוָ֛ה","a":" ","g":"of.Yahweh","l":"יהוה","s":"3068","m":"Np","tr":"yəhwāh"},{"t":"אֶל","a":"־","g":"to","l":"אֶל","s":"413","m":"R","tr":"ʾel-"},{"t":"יוֹנָ֖ה","a":" ","g":"Jonah","l":"יוֹנָה","s":"3124","m":"Np","tr":"yônāh"},{"t":"שֵׁנִ֥ית","a":" ","g":"a.second.[time]","l":"שֵׁנִי","s":"8145","m":"Aofsa","tr":"šēniyṯ"},{"t":"לֵ","a":"","g":"(cmp)","l":"לְ","s":"3807","m":"R","tr":"lē"},{"t":"אמֹֽר","a":"׃","g":"saying","l":"אָמַר","s":"559","m":"Vqc","tr":"ʾmōr:"}],"3:2":[{"t":"ק֛וּם","a":" ","g":"arise","l":"קוּם","s":"6965","m":"Vqv2ms","tr":"qûm"},{"t":"לֵ֥ךְ","a":" ","g":"go","l":"הלך","s":"1980","m":"Vqv2ms","tr":"lēḵ"},{"t":"אֶל","a":"־","g":"to","l":"אֶל","s":"413","m":"R","tr":"ʾel-"},{"t":"נִֽינְוֵ֖ה","a":" ","g":"Nineveh","l":"נִינְוֵה","s":"5210","m":"Np","tr":"niynəwēh"},{"t":"הָ","a":"","g":"the","l":"הַ","s":"1886","m":"Td","tr":"hā"},{"t":"עִ֣יר","a":" ","g":"city","l":"עִיר","s":"5892","m":"Ncfsa","tr":"ʿiyr"},{"t":"הַ","a":"","g":"(the)","l":"הַ","s":"1886","m":"Td","tr":"ha"},{"t":"גְּדוֹלָ֑ה","a":" ","g":"great","l":"גָּדוֹל","s":"1419","m":"Aafsa","tr":"gəḏôlāh"},{"t":"וִּ","a":"","g":"and","l":"וְ","s":"2050","m":"C","tr":"wwi"},{"t":"קְרָ֤א","a":"","g":"call.out","l":"קָרָא","s":"7121","m":"Vqv2ms","tr":"qərāʾ"},{"t":"אֵלֶ֨י","a":"","g":"against","l":"אֶל","s":"413","m":"R","tr":""},{"t":"הָ֙","a":" ","g":"it","l":"הוּא","s":"1886","m":"Sp3fs","tr":""},{"t":"אֶת","a":"־","g":"(et)","l":"אֵת","s":"853","m":"To","tr":"ʾeṯ-"},{"t":"הַ","a":"","g":"the","l":"הַ","s":"1886","m":"Td","tr":"ha"},{"t":"קְּרִיאָ֔ה","a":" ","g":"proclamation","l":"קְרִיאָה","s":"7150","m":"Ncfsa","tr":"qqərîʾāh"},{"t":"אֲשֶׁ֥ר","a":" ","g":"which","l":"אֲשֶׁר","s":"834","m":"Tr","tr":"ʾăšer"},{"t":"אָנֹכִ֖י","a":" ","g":"I","l":"אָנֹכִי","s":"595","m":"Pp1cs","tr":"ʾānōḵiy"},{"t":"דֹּבֵ֥ר","a":" ","g":"[am].speaking","l":"דָבַר","s":"1696","m":"Vqrmsa","tr":"dōḇēr"},{"t":"אֵלֶֽי","a":"","g":"to","l":"אֶל","s":"413","m":"R","tr":""},{"t":"ךָ","a":"׃","g":"you","l":"הוּא","s":"3509","m":"Sp2ms","tr":""}],"3:3":[{"t":"וַ","a":"","g":"and","l":"וְ","s":"2050","m":"C","tr":"wa"},{"t":"יָּ֣קָם","a":" ","g":"he.arose","l":"קוּם","s":"6965","m":"Vqw3ms","tr":"yyāqām"},{"t":"יוֹנָ֗ה","a":" ","g":"Jonah","l":"יוֹנָה","s":"3124","m":"Np","tr":"yônāh"},{"t":"וַ","a":"","g":"and","l":"וְ","s":"2050","m":"C","tr":"wa"},{"t":"יֵּ֛לֶךְ","a":" ","g":"he.went","l":"הלך","s":"1980","m":"Vqw3ms","tr":"yyēleḵ"},{"t":"אֶל","a":"־","g":"to","l":"אֶל","s":"413","m":"R","tr":"ʾel-"},{"t":"נִֽינְוֶ֖ה","a":"","g":"Nineveh","l":"נִינְוֵה","s":"5210","m":"Np","tr":"niynəweh"},{"t":"כִּ","a":"","g":"according","l":"כְּ","s":"3509","m":"R","tr":"ki"},{"t":"דְבַ֣ר","a":" ","g":"to.the.word","l":"דָּבָר","s":"1697","m":"Ncmsc","tr":"ḏəḇar"},{"t":"יְהוָ֑ה","a":" ","g":"of.Yahweh","l":"יהוה","s":"3068","m":"Np","tr":"yəhwāh"},{"t":"וְ","a":"","g":"and","l":"וְ","s":"2050","m":"C","tr":"wə"},{"t":"נִֽינְוֵ֗ה","a":" ","g":"Nineveh","l":"נִינְוֵה","s":"5210","m":"Np","tr":"niynəwēh"},{"t":"הָיְתָ֤ה","a":" ","g":"it.was","l":"הָיָה","s":"1961","m":"Vqp3fs","tr":"hāyəṯāh"},{"t":"עִיר","a":"־","g":"a.city","l":"עִיר","s":"5892","m":"Ncfsa","tr":"ʿîr-"},{"t":"גְּדוֹלָה֙","a":" ","g":"great","l":"גָּדוֹל","s":"1419","m":"Aafsa","tr":"gəḏôlāh"},{"t":"לֵֽ","a":"","g":"to","l":"לְ","s":"3807","m":"R","tr":"lē"},{"t":"אלֹהִ֔ים","a":" ","g":"God","l":"אֱלֹהִים","s":"430","m":"Ncmpa","tr":"ʾlōhiym"},{"t":"מַהֲלַ֖ךְ","a":" ","g":"a.journey","l":"מַהֲלָךְ","s":"4109","m":"Ncmsc","tr":"mahălaḵ"},{"t":"שְׁלֹ֥שֶׁת","a":" ","g":"of.three","l":"שָׁלֹשׁ","s":"7969","m":"Acmsc","tr":"šəlōšeṯ"},{"t":"יָמִֽים","a":"׃","g":"days","l":"יוֹם","s":"3117","m":"Ncmpa","tr":"yāmiym:"}],"3:4":[{"t":"וַ","a":"","g":"and","l":"וְ","s":"2050","m":"C","tr":"wa"},{"t":"יָּ֤חֶל","a":" ","g":"he.began","l":"חָלַל","s":"2490","m":"Vhw3ms","tr":"yyāḥel"},{"t":"יוֹנָה֙","a":" ","g":"Jonah","l":"יוֹנָה","s":"3124","m":"Np","tr":"yônāh"},{"t":"לָ","a":"","g":"to","l":"לְ","s":"3807","m":"R","tr":"lā"},{"t":"ב֣וֹא","a":" ","g":"go","l":"בּוֹא","s":"935","m":"Vqc","tr":"ḇôʾ"},{"t":"בָ","a":"","g":"in","l":"בְּ","s":"871","m":"Rd","tr":"ḇā"},{"t":"","a":"","g":"the","l":"הַ","s":"1886","m":"Td","tr":"–"},{"t":"עִ֔יר","a":" ","g":"city","l":"עִיר","s":"5892","m":"Ncfsa","tr":"ʿiyr"},{"t":"מַהֲלַ֖ךְ","a":" ","g":"a.journey","l":"מַהֲלָךְ","s":"4109","m":"Ncmsc","tr":"mahălaḵ"},{"t":"י֣וֹם","a":" ","g":"of.a.day","l":"יוֹם","s":"3117","m":"Ncmsa","tr":"yôm"},{"t":"אֶחָ֑ד","a":" ","g":"one","l":"אֶחָד","s":"259","m":"Acmsa","tr":"ʾeḥāḏ"},{"t":"וַ","a":"","g":"and","l":"וְ","s":"2050","m":"C","tr":"wa"},{"t":"יִּקְרָא֙","a":" ","g":"he.proclaimed","l":"קָרָא","s":"7121","m":"Vqw3ms","tr":"yyiqrāʾ"},{"t":"וַ","a":"","g":"and","l":"וְ","s":"2050","m":"C","tr":"wa"},{"t":"יֹּאמַ֔ר","a":" ","g":"he.said","l":"אָמַר","s":"559","m":"Vqw3ms","tr":"yyōʾmar"},{"t":"ע֚וֹד","a":" ","g":"yet","l":"עוֹד","s":"5750","m":"D","tr":"ʿôḏ"},{"t":"אַרְבָּעִ֣ים","a":" ","g":"forty","l":"אַרְבַּע","s":"705","m":"Acbpa","tr":"ʾarbāʿiym"},{"t":"י֔וֹם","a":" ","g":"day[s]","l":"יוֹם","s":"3117","m":"Ncmsa","tr":"yôm"},{"t":"וְ","a":"","g":"and","l":"וְ","s":"2050","m":"C","tr":"wə"},{"t":"נִֽינְוֵ֖ה","a":" ","g":"Nineveh","l":"נִינְוֵה","s":"5210","m":"Np","tr":"niynəwēh"},{"t":"נֶהְפָּֽכֶת","a":"׃","g":"[is].about.to.be.overturned","l":"הָפַךְ","s":"2015","m":"VNrfsa","tr":"nehpāḵeṯ:"}],"3:5":[{"t":"וַֽ","a":"","g":"and","l":"וְ","s":"2050","m":"C","tr":"wa"},{"t":"יַּאֲמִ֛ינוּ","a":" ","g":"they.believed","l":"אָמַן","s":"539","m":"Vhw3mp","tr":"yyaʾămiynû"},{"t":"אַנְשֵׁ֥י","a":" ","g":"the.people","l":"אִישׁ","s":"376","m":"Ncmpc","tr":"ʾanšēy"},{"t":"נִֽינְוֵ֖ה","a":" ","g":"of.Nineveh","l":"נִינְוֵה","s":"5210","m":"Np","tr":"niynəwēh"},{"t":"בֵּֽ","a":"","g":"in","l":"בְּ","s":"871","m":"R","tr":"bē"},{"t":"אלֹהִ֑ים","a":" ","g":"God","l":"אֱלֹהִים","s":"430","m":"Ncmpa","tr":"ʾlōhiym"},{"t":"וַ","a":"","g":"and","l":"וְ","s":"2050","m":"C","tr":"wa"},{"t":"יִּקְרְאוּ","a":"־","g":"they.proclaimed","l":"קָרָא","s":"7121","m":"Vqw3mp","tr":"yyiqrəʾû-"},{"t":"צוֹם֙","a":" ","g":"a.fast","l":"צוֹם","s":"6685","m":"Ncmsa","tr":"ṣôm"},{"t":"וַ","a":"","g":"and","l":"וְ","s":"2050","m":"C","tr":"wa"},{"t":"יִּלְבְּשׁ֣וּ","a":" ","g":"they.wore","l":"לָבֵשׁ","s":"3847","m":"Vqw3mp","tr":"yyilbəšû"},{"t":"שַׂקִּ֔ים","a":" ","g":"sackcloth(s)","l":"שַׂק","s":"8242","m":"Ncmpa","tr":"śaqqiym"},{"t":"מִ","a":"","g":"from","l":"מִן","s":"4480","m":"R","tr":"mi"},{"t":"גְּדוֹלָ֖","a":"","g":"their","l":"גָּדוֹל","s":"1419","m":"Aamsc","tr":""},{"t":"ם","a":" ","g":"great","l":"הוּא","s":"3963","m":"Sp3mp","tr":""},{"t":"וְ","a":"","g":"and","l":"וְ","s":"2050","m":"R","tr":"wə"},{"t":"עַד","a":"־","g":"unto","l":"עַד","s":"5704","m":"R","tr":"ʿaḏ-"},{"t":"קְטַנָּֽ","a":"","g":"their","l":"קָטָן","s":"6996","m":"Aamsc","tr":""},{"t":"ם","a":"׃","g":"insignificant","l":"הוּא","s":"3963","m":"Sp3mp","tr":""}],"3:6":[{"t":"וַ","a":"","g":"and","l":"וְ","s":"2050","m":"C","tr":"wa"},{"t":"יִּגַּ֤ע","a":" ","g":"it.reached","l":"נָגַע","s":"5060","m":"Vqw3ms","tr":"yyiggaʿ"},{"t":"הַ","a":"","g":"the","l":"הַ","s":"1886","m":"Td","tr":"ha"},{"t":"דָּבָר֙","a":" ","g":"word","l":"דָּבָר","s":"1697","m":"Ncmsa","tr":"dāḇār"},{"t":"אֶל","a":"־","g":"to","l":"אֶל","s":"413","m":"R","tr":"ʾel-"},{"t":"מֶ֣לֶך","a":"","g":"the.king","l":"מֶלֶךְ","s":"4428","m":"Ncmsc","tr":"meleḵ"},{"t":"נִֽינְוֵ֔ה","a":" ","g":"of.Nineveh","l":"נִינְוֵה","s":"5210","m":"Np","tr":"niynəwēh"},{"t":"וַ","a":"","g":"and","l":"וְ","s":"2050","m":"C","tr":"wa"},{"t":"יָּ֨קָם֙","a":" ","g":"he.arose","l":"קוּם","s":"6965","m":"Vqw3ms","tr":"yyāqām"},{"t":"מִ","a":"","g":"from","l":"מִן","s":"4480","m":"R","tr":"mi"},{"t":"כִּסְא֔","a":"","g":"throne","l":"כִּסֵּא","s":"3678","m":"Ncmsc","tr":""},{"t":"וֹ","a":" ","g":"his","l":"הוּא","s":"2050","m":"Sp3ms","tr":""},{"t":"וַ","a":"","g":"and","l":"וְ","s":"2050","m":"C","tr":"wa"},{"t":"יַּעֲבֵ֥ר","a":" ","g":"he.took.off","l":"עָבַר","s":"5674","m":"Vhw3ms","tr":"yyaʿăḇēr"},{"t":"אַדַּרְתּ֖","a":"","g":"cloak","l":"אַדֶּרֶת","s":"155","m":"Ncfsc","tr":""},{"t":"וֹ","a":" ","g":"his","l":"הוּא","s":"2050","m":"Sp3ms","tr":""},{"t":"מֵֽ","a":"","g":"from","l":"מִן","s":"4480","m":"R","tr":"mē"},{"t":"עָלָ֑י","a":"","g":"on","l":"עַל","s":"5921","m":"R","tr":""},{"t":"ו","a":" ","g":"him","l":"הוּא","s":"2050","m":"Sp3ms","tr":""},{"t":"וַ","a":"","g":"and","l":"וְ","s":"2050","m":"C","tr":"wa"},{"t":"יְכַ֣ס","a":" ","g":"he.covered","l":"כָּסָה","s":"3680","m":"Vpw3ms","tr":"yəḵas"},{"t":"שַׂ֔ק","a":" ","g":"sackcloth","l":"שַׂק","s":"8242","m":"Ncmsa","tr":"śaq"},{"t":"וַ","a":"","g":"and","l":"וְ","s":"2050","m":"C","tr":"wa"},{"t":"יֵּ֖שֶׁב","a":" ","g":"he.sat","l":"יָשַׁב","s":"3427","m":"Vqw3ms","tr":"yyēšeḇ"},{"t":"עַל","a":"־","g":"on","l":"עַל","s":"5921","m":"R","tr":"ʿal-"},{"t":"הָ","a":"","g":"(the)","l":"הַ","s":"1886","m":"Td","tr":"hā"},{"t":"אֵֽפֶר","a":"׃","g":"ash[es]","l":"אֵפֶר","s":"665","m":"Ncmsa","tr":"ʾēp̄er:"}],"3:7":[{"t":"וַ","a":"","g":"and","l":"וְ","s":"2050","m":"C","tr":"wa"},{"t":"יַּזְעֵ֗ק","a":" ","g":"he.had.a.proclamation.made","l":"זָעַק","s":"2199","m":"Vhw3ms","tr":"yyazʿēq"},{"t":"וַ","a":"","g":"and","l":"וְ","s":"2050","m":"C","tr":"wa"},{"t":"יֹּ֨אמֶר֙","a":" ","g":"he.said","l":"אָמַר","s":"559","m":"Vqw3ms","tr":"yyōʾmer"},{"t":"בְּ","a":"","g":"in","l":"בְּ","s":"871","m":"R","tr":"bə"},{"t":"נִֽינְוֵ֔ה","a":" ","g":"Nineveh","l":"נִינְוֵה","s":"5210","m":"Np","tr":"niynəwēh"},{"t":"מִ","a":"","g":"from","l":"מִן","s":"4480","m":"R","tr":"mi"},{"t":"טַּ֧עַם","a":" ","g":"the.decree","l":"טַעַם","s":"2940","m":"Ncmsc","tr":"ṭṭaʿam"},{"t":"הַ","a":"","g":"of","l":"הַ","s":"1886","m":"Td","tr":"ha"},{"t":"מֶּ֛לֶךְ","a":" ","g":"the.king","l":"מֶלֶךְ","s":"4428","m":"Ncmsa","tr":"mmeleḵ"},{"t":"וּ","a":"","g":"and","l":"וְ","s":"2050","m":"C","tr":"û"},{"t":"גְדֹלָ֖י","a":"","g":"his.great","l":"גָּדוֹל","s":"1419","m":"Aampc","tr":""},{"t":"ו","a":" ","g":"[people]","l":"הוּא","s":"2050","m":"Sp3ms","tr":""},{"t":"לֵ","a":"","g":"(cmp)","l":"לְ","s":"3807","m":"R","tr":"lē"},{"t":"אמֹ֑ר","a":" ","g":"say","l":"אָמַר","s":"559","m":"Vqc","tr":"ʾmōr"},{"t":"הָ","a":"","g":"the","l":"הַ","s":"1886","m":"Td","tr":"hā"},{"t":"אָדָ֨ם","a":" ","g":"people","l":"אָדָם","s":"120","m":"Ncmsa","tr":"ʾāḏām"},{"t":"וְ","a":"","g":"and","l":"וְ","s":"2050","m":"C","tr":"wə"},{"t":"הַ","a":"","g":"the","l":"הַ","s":"1886","m":"Td","tr":"ha"},{"t":"בְּהֵמָ֜ה","a":" ","g":"livestock","l":"בְּהֵמָה","s":"929","m":"Ncfsa","tr":"bəhēmāh"},{"t":"הַ","a":"","g":"the","l":"הַ","s":"1886","m":"Td","tr":"ha"},{"t":"בָּקָ֣ר","a":" ","g":"cattle","l":"בָּקָר","s":"1241","m":"Ncbsa","tr":"bāqār"},{"t":"וְ","a":"","g":"and","l":"וְ","s":"2050","m":"C","tr":"wə"},{"t":"הַ","a":"","g":"the","l":"הַ","s":"1886","m":"Td","tr":"ha"},{"t":"צֹּ֗אן","a":" ","g":"flock[s]","l":"צֹאן","s":"6629","m":"Ncbsa","tr":"ṣṣōʾn"},{"t":"אַֽל","a":"־","g":"not","l":"אַל","s":"408","m":"Tn","tr":"ʾal-"},{"t":"יִטְעֲמוּ֙","a":" ","g":"let.them.taste","l":"טָעַם","s":"2938","m":"Vqj3mp","tr":"yiṭʿămû"},{"t":"מְא֔וּמָה","a":" ","g":"anything","l":"מְאוּמָה","s":"3972","m":"Ncfsa","tr":"məʾûmâ"},{"t":"אַ֨ל","a":"־","g":"not","l":"אַל","s":"408","m":"Tn","tr":"ʾal-"},{"t":"יִרְע֔וּ","a":" ","g":"let.them.graze","l":"רָעָה","s":"7462","m":"Vqj3mp","tr":"yirʿû"},{"t":"וּ","a":"","g":"and","l":"וְ","s":"2050","m":"C","tr":"û"},{"t":"מַ֖יִם","a":" ","g":"water","l":"מַיִם","s":"4325","m":"Ncmsa","tr":"mayim"},{"t":"אַל","a":"־","g":"not","l":"אַל","s":"408","m":"Tn","tr":"ʾal-"},{"t":"יִשְׁתּֽוּ","a":"׃","g":"let.them.drink","l":"שָׁתָה","s":"8354","m":"Vqj3mp","tr":"yištû:"}],"3:8":[{"t":"וְ","a":"","g":"and","l":"וְ","s":"2050","m":"C","tr":"wə"},{"t":"יִתְכַּסּ֣וּ","a":" ","g":"let.them.cover.themselves","l":"כָּסָה","s":"3680","m":"Vti3mp","tr":"yiṯkassû"},{"t":"שַׂקִּ֗ים","a":" ","g":"sackcloth(s)","l":"שַׂק","s":"8242","m":"Ncmpa","tr":"śaqqiym"},{"t":"הָֽ","a":"","g":"the","l":"הַ","s":"1886","m":"Td","tr":"hā"},{"t":"אָדָם֙","a":" ","g":"people","l":"אָדָם","s":"120","m":"Ncmsa","tr":"ʾāḏām"},{"t":"וְ","a":"","g":"and","l":"וְ","s":"2050","m":"C","tr":"wə"},{"t":"הַ","a":"","g":"the","l":"הַ","s":"1886","m":"Td","tr":"ha"},{"t":"בְּהֵמָ֔ה","a":" ","g":"livestock","l":"בְּהֵמָה","s":"929","m":"Ncfsa","tr":"bəhēmāh"},{"t":"וְ","a":"","g":"and","l":"וְ","s":"2050","m":"C","tr":"wə"},{"t":"יִקְרְא֥וּ","a":" ","g":"let.them.call.out","l":"קָרָא","s":"7121","m":"Vqi3mp","tr":"yiqrəʾû"},{"t":"אֶל","a":"־","g":"to","l":"אֶל","s":"413","m":"R","tr":"ʾel-"},{"t":"אֱלֹהִ֖ים","a":" ","g":"God","l":"אֱלֹהִים","s":"430","m":"Ncmpa","tr":"ʾĕlōhiym"},{"t":"בְּ","a":"","g":"with","l":"בְּ","s":"871","m":"R","tr":"bə"},{"t":"חָזְקָ֑ה","a":" ","g":"force","l":"חׇזְקָה","s":"2394","m":"Ncfsa","tr":"ḥāzəqāh"},{"t":"וְ","a":"","g":"and","l":"וְ","s":"2050","m":"C","tr":"wə"},{"t":"יָשֻׁ֗בוּ","a":" ","g":"let.them.turn.back","l":"שׁוּב","s":"7725","m":"Vqi3mp","tr":"yāšuḇû"},{"t":"אִ֚ישׁ","a":" ","g":"everyone","l":"אִישׁ","s":"376","m":"Ncmsa","tr":"ʾîš"},{"t":"מִ","a":"","g":"from","l":"מִן","s":"4480","m":"R","tr":"mi"},{"t":"דַּרְכּ֣","a":"","g":"way","l":"דֶּרֶךְ","s":"1870","m":"Ncbsc","tr":""},{"t":"וֹ","a":" ","g":"his","l":"הוּא","s":"2050","m":"Sp3ms","tr":""},{"t":"הָֽ","a":"","g":"(the)","l":"הַ","s":"1886","m":"Td","tr":"hā"},{"t":"רָעָ֔ה","a":" ","g":"evil","l":"רַע","s":"7451","m":"Aafsa","tr":"rāʿāh"},{"t":"וּ","a":"","g":"and","l":"וְ","s":"2050","m":"C","tr":"û"},{"t":"מִן","a":"־","g":"from","l":"מִן","s":"4480","m":"R","tr":"min-"},{"t":"הֶ","a":"","g":"the","l":"הַ","s":"1886","m":"Td","tr":"he"},{"t":"חָמָ֖ס","a":" ","g":"violence","l":"חָמָס","s":"2555","m":"Ncmsa","tr":"ḥāmās"},{"t":"אֲשֶׁ֥ר","a":" ","g":"which","l":"אֲשֶׁר","s":"834","m":"Tr","tr":"ʾăšer"},{"t":"בְּ","a":"","g":"[is].in","l":"בְּ","s":"871","m":"R","tr":"bə"},{"t":"כַפֵּי","a":"","g":"palms","l":"כַּף","s":"3709","m":"Ncfdc","tr":""},{"t":"הֶֽם","a":"׃","g":"their","l":"הוּא","s":"3963","m":"Sp3mp","tr":""}],"3:9":[{"t":"מִֽי","a":"־","g":"who?","l":"מִי","s":"4310","m":"Ti","tr":"miy-"},{"t":"יוֹדֵ֣עַ","a":" ","g":"[is].knowing","l":"יָדַע","s":"3045","m":"Vqrmsa","tr":"yôḏēᵃʿ"},{"t":"יָשׁ֔וּב","a":" ","g":"he.will.turn","l":"שׁוּב","s":"7725","m":"Vqi3ms","tr":"yāšûḇ"},{"t":"וְ","a":"","g":"and","l":"וְ","s":"2050","m":"C","tr":"wə"},{"t":"נִחַ֖ם","a":" ","g":"he.will.relent","l":"נָחַם","s":"5162","m":"VNq3ms","tr":"niḥam"},{"t":"הָ","a":"","g":"(the)","l":"הַ","s":"1886","m":"Td","tr":"hā"},{"t":"אֱלֹהִ֑ים","a":" ","g":"God","l":"אֱלֹהִים","s":"430","m":"Ncmpa","tr":"ʾĕlōhiym"},{"t":"וְ","a":"","g":"and","l":"וְ","s":"2050","m":"C","tr":"wə"},{"t":"שָׁ֛ב","a":" ","g":"he.will.turn.back","l":"שׁוּב","s":"7725","m":"Vqq3ms","tr":"šāḇ"},{"t":"מֵ","a":"","g":"from","l":"מִן","s":"4480","m":"R","tr":"mē"},{"t":"חֲר֥וֹן","a":" ","g":"the.burning","l":"חָרוֹן","s":"2740","m":"Ncmsc","tr":"ḥărôn"},{"t":"אַפּ֖","a":"","g":"his.anger","l":"אַף","s":"639","m":"Ncmsc","tr":""},{"t":"וֹ","a":" ","g":"his","l":"הוּא","s":"2050","m":"Sp3ms","tr":""},{"t":"וְ","a":"","g":"and","l":"וְ","s":"2050","m":"C","tr":"wə"},{"t":"לֹ֥א","a":" ","g":"not","l":"לֹא","s":"3808","m":"Tn","tr":"lōʾ"},{"t":"נֹאבֵֽד","a":"׃","g":"we.will.perish","l":"אָבַד","s":"6","m":"Vqi1cp","tr":"nōʾḇēḏ:"}],"3:10":[{"t":"וַ","a":"","g":"and","l":"וְ","s":"2050","m":"C","tr":"wa"},{"t":"יַּ֤רְא","a":" ","g":"he.saw","l":"רָאָה","s":"7200","m":"Vqw3ms","tr":"yyarəʾ"},{"t":"הָֽ","a":"","g":"(the)","l":"הַ","s":"1886","m":"Td","tr":"hā"},{"t":"אֱלֹהִים֙","a":" ","g":"God","l":"אֱלֹהִים","s":"430","m":"Ncmpa","tr":"ʾĕlōhîm"},{"t":"אֶֽת","a":"־","g":"(et)","l":"אֵת","s":"853","m":"To","tr":"ʾeṯ-"},{"t":"מַ֣עֲשֵׂי","a":"","g":"deeds","l":"מַעֲשֶׂה","s":"4639","m":"Ncmpc","tr":""},{"t":"הֶ֔ם","a":" ","g":"their","l":"הוּא","s":"3963","m":"Sp3mp","tr":""},{"t":"כִּי","a":"־","g":"(dm).that","l":"כִּי","s":"3588","m":"C","tr":"kî-"},{"t":"שָׁ֖בוּ","a":" ","g":"they.turned.back","l":"שׁוּב","s":"7725","m":"Vqp3cp","tr":"šāḇû"},{"t":"מִ","a":"","g":"from","l":"מִן","s":"4480","m":"R","tr":"mi"},{"t":"דַּרְכָּ֣","a":"","g":"way","l":"דֶּרֶךְ","s":"1870","m":"Ncbsc","tr":""},{"t":"ם","a":" ","g":"their","l":"הוּא","s":"3963","m":"Sp3mp","tr":""},{"t":"הָ","a":"","g":"(the)","l":"הַ","s":"1886","m":"Td","tr":"hā"},{"t":"רָעָ֑ה","a":" ","g":"evil","l":"רַע","s":"7451","m":"Aafsa","tr":"rāʿāh"},{"t":"וַ","a":"","g":"and","l":"וְ","s":"2050","m":"C","tr":"wa"},{"t":"יִּנָּ֣חֶם","a":" ","g":"he.relented","l":"נָחַם","s":"5162","m":"VNw3ms","tr":"yyinnāḥem"},{"t":"הָ","a":"","g":"(the)","l":"הַ","s":"1886","m":"Td","tr":"hā"},{"t":"אֱלֹהִ֗ים","a":" ","g":"God","l":"אֱלֹהִים","s":"430","m":"Ncmpa","tr":"ʾĕlōhiym"},{"t":"עַל","a":"־","g":"on","l":"עַל","s":"5921","m":"R","tr":"ʿal-"},{"t":"הָ","a":"","g":"the","l":"הַ","s":"1886","m":"Td","tr":"hā"},{"t":"רָעָ֛ה","a":" ","g":"evil","l":"רָעָה","s":"7451","m":"Ncfsa","tr":"rāʿāh"},{"t":"אֲשֶׁר","a":"־","g":"which","l":"אֲשֶׁר","s":"834","m":"Tr","tr":"ʾăšer-"},{"t":"דִּבֶּ֥ר","a":" ","g":"he.had.said","l":"דָבַר","s":"1696","m":"Vpp3ms","tr":"dibber"},{"t":"לַ","a":"","g":"to","l":"לְ","s":"3807","m":"R","tr":"la"},{"t":"עֲשׂוֹת","a":"־","g":"do","l":"עָשָׂה","s":"6213","m":"Vqc","tr":"ʿăśôṯ-"},{"t":"לָ","a":"","g":"to","l":"לְ","s":"3807","m":"R","tr":""},{"t":"הֶ֖ם","a":" ","g":"them","l":"הוּא","s":"3963","m":"Sp3mp","tr":""},{"t":"וְ","a":"","g":"and","l":"וְ","s":"2050","m":"C","tr":"wə"},{"t":"לֹ֥א","a":" ","g":"not","l":"לֹא","s":"3808","m":"Tn","tr":"lōʾ"},{"t":"עָשָֽׂה","a":"׃","g":"he.did.[it]","l":"עָשָׂה","s":"6213","m":"Vqp3ms","tr":"ʿāśāh:"}],"4:1":[{"t":"וַ","a":"","g":"and","l":"וְ","s":"2050","m":"C","tr":"wa"},{"t":"יֵּ֥רַע","a":" ","g":"it.was.displeasing","l":"רָעַע","s":"7489","m":"Vqw3ms","tr":"yyēraʿ"},{"t":"אֶל","a":"־","g":"to","l":"אֶל","s":"413","m":"R","tr":"ʾel-"},{"t":"יוֹנָ֖ה","a":" ","g":"Jonah","l":"יוֹנָה","s":"3124","m":"Np","tr":"yônāh"},{"t":"רָעָ֣ה","a":" ","g":"displeasure","l":"רָעָה","s":"7451","m":"Ncfsa","tr":"rāʿāh"},{"t":"גְדוֹלָ֑ה","a":" ","g":"great","l":"גָּדוֹל","s":"1419","m":"Aafsa","tr":"ḡəḏôlāh"},{"t":"וַ","a":"","g":"and","l":"וְ","s":"2050","m":"C","tr":"wa"},{"t":"יִּ֖חַר","a":" ","g":"it.burned","l":"חָרָה","s":"2734","m":"Vqw3ms","tr":"yyiḥar"},{"t":"לֽ","a":"","g":"to","l":"לְ","s":"3807","m":"R","tr":""},{"t":"וֹ","a":"׃","g":"him","l":"הוּא","s":"2050","m":"Sp3ms","tr":""}],"4:2":[{"t":"וַ","a":"","g":"and","l":"וְ","s":"2050","m":"C","tr":"wa"},{"t":"יִּתְפַּלֵּ֨ל","a":" ","g":"he.prayed","l":"פָּלַל","s":"6419","m":"Vtw3ms","tr":"yyiṯpallēl"},{"t":"אֶל","a":"־","g":"to","l":"אֶל","s":"413","m":"R","tr":"ʾel-"},{"t":"יְהוָ֜ה","a":" ","g":"Yahweh","l":"יהוה","s":"3068","m":"Np","tr":"yəhwāh"},{"t":"וַ","a":"","g":"and","l":"וְ","s":"2050","m":"C","tr":"wa"},{"t":"יֹּאמַ֗ר","a":" ","g":"he.said","l":"אָמַר","s":"559","m":"Vqw3ms","tr":"yyōʾmar"},{"t":"אָנָּ֤ה","a":" ","g":"please!","l":"אָנָּא","s":"577","m":"Tj","tr":"ʾonnāh"},{"t":"יְהוָה֙","a":" ","g":"O.Yahweh","l":"יהוה","s":"3068","m":"Np","tr":"yhwh"},{"t":"הֲ","a":"","g":"?","l":"הֲ","s":"1886","m":"Ti","tr":"hă"},{"t":"לוֹא","a":"־","g":"not","l":"לֹא","s":"3808","m":"Tn","tr":"lôʾ-"},{"t":"זֶ֣ה","a":" ","g":"[was].this","l":"זֶה","s":"2088","m":"Pdxms","tr":"zeh"},{"t":"דְבָרִ֗","a":"","g":"word","l":"דָּבָר","s":"1697","m":"Ncmsc","tr":""},{"t":"י","a":" ","g":"my","l":"הוּא","s":"2967","m":"Sp1cs","tr":""},{"t":"עַד","a":"־","g":"until","l":"עַד","s":"5704","m":"R","tr":"ʿaḏ-"},{"t":"הֱיוֹתִ","a":"","g":"was","l":"הָיָה","s":"1961","m":"Vqc","tr":""},{"t":"י֙","a":" ","g":"I","l":"הוּא","s":"5204","m":"Sp1cs","tr":""},{"t":"עַל","a":"־","g":"on","l":"עַל","s":"5921","m":"R","tr":"ʿal-"},{"t":"אַדְמָתִ֔","a":"","g":"land","l":"אֲדָמָה","s":"127","m":"Ncfsc","tr":""},{"t":"י","a":" ","g":"my.own","l":"הוּא","s":"2967","m":"Sp1cs","tr":""},{"t":"עַל","a":"־","g":"therefore","l":"עַל","s":"5921","m":"R","tr":""},{"t":"כֵּ֥ן","a":" ","g":"","l":"כֵּן","s":"3651","m":"Tm","tr":""},{"t":"קִדַּ֖מְתִּי","a":" ","g":"I.did.the.first.time","l":"קָדַם","s":"6923","m":"Vpp1cs","tr":"qiddamətî"},{"t":"לִ","a":"","g":"to","l":"לְ","s":"3807","m":"R","tr":"li"},{"t":"בְרֹ֣חַ","a":" ","g":"flee","l":"בָּרַח","s":"1272","m":"Vqc","tr":"ḇərōᵃḥ"},{"t":"תַּרְשִׁ֑ישָׁ","a":"","g":"to","l":"תַּרְשִׁישׁ","s":"8659","m":"Np","tr":""},{"t":"ה","a":" ","g":"Tarshish","l":"ה","s":"1886","m":"Sd","tr":""},{"t":"כִּ֣י","a":" ","g":"(dm)","l":"כִּי","s":"3588","m":"C","tr":"kiy"},{"t":"יָדַ֗עְתִּי","a":" ","g":"I.knew","l":"יָדַע","s":"3045","m":"Vqp1cs","tr":"yāḏaʿətî"},{"t":"כִּ֤י","a":" ","g":"(dm).that","l":"כִּי","s":"3588","m":"C","tr":"kiy"},{"t":"אַתָּה֙","a":" ","g":"you","l":"אַתָּה","s":"859","m":"Pp2ms","tr":"ʾattāh"},{"t":"אֵֽל","a":"־","g":"[are].a.God","l":"אֵל","s":"410","m":"Ncmsa","tr":"ʾēl-"},{"t":"חַנּ֣וּן","a":" ","g":"gracious","l":"חַנּוּן","s":"2587","m":"Aamsa","tr":"ḥannûn"},{"t":"וְ","a":"","g":"and","l":"וְ","s":"2050","m":"C","tr":"wə"},{"t":"רַח֔וּם","a":" ","g":"compassionate","l":"רַחוּם","s":"7349","m":"Aamsa","tr":"raḥûm"},{"t":"אֶ֤רֶךְ","a":" ","g":"long","l":"אָרֵךְ","s":"750","m":"Aamsc","tr":"ʾereḵ"},{"t":"אַפַּ֨יִם֙","a":" ","g":"of.anger(s)","l":"אַף","s":"639","m":"Ncmda","tr":"ʾappayim"},{"t":"וְ","a":"","g":"and","l":"וְ","s":"2050","m":"C","tr":"wə"},{"t":"רַב","a":"־","g":"great","l":"רַב","s":"7227","m":"Aamsc","tr":"raḇ-"},{"t":"חֶ֔סֶד","a":" ","g":"of.covenant.loyalty","l":"חֶסֶד","s":"2617","m":"Ncmsa","tr":"ḥeseḏ"},{"t":"וְ","a":"","g":"and.[who]","l":"וְ","s":"2050","m":"C","tr":"wə"},{"t":"נִחָ֖ם","a":" ","g":"relents","l":"נָחַם","s":"5162","m":"VNrmsa","tr":"niḥām"},{"t":"עַל","a":"־","g":"on","l":"עַל","s":"5921","m":"R","tr":"ʿal-"},{"t":"הָ","a":"","g":"(the)","l":"הַ","s":"1886","m":"Td","tr":"hā"},{"t":"רָעָֽה","a":"׃","g":"evil","l":"רָעָה","s":"7451","m":"Ncfsa","tr":"rāʿāh:"}],"4:3":[{"t":"וְ","a":"","g":"and","l":"וְ","s":"2050","m":"C","tr":"wə"},{"t":"עַתָּ֣ה","a":" ","g":"therefore","l":"עַתָּה","s":"6258","m":"D","tr":"ʿattāh"},{"t":"יְהוָ֔ה","a":" ","g":"O.Yahweh","l":"יהוה","s":"3068","m":"Np","tr":"yəhwāh"},{"t":"קַח","a":"־","g":"take","l":"לָקַח","s":"3947","m":"Vqv2ms","tr":"qaḥ-"},{"t":"נָ֥א","a":" ","g":"please","l":"נָא","s":"4994","m":"Te","tr":"nāʾ"},{"t":"אֶת","a":"־","g":"(et)","l":"אֵת","s":"853","m":"To","tr":"ʾeṯ-"},{"t":"נַפְשִׁ֖","a":"","g":"life","l":"נֶפֶשׁ","s":"5315","m":"Ncbsc","tr":""},{"t":"י","a":" ","g":"my","l":"הוּא","s":"2967","m":"Sp1cs","tr":""},{"t":"מִמֶּ֑","a":"","g":"from","l":"מִן","s":"4480","m":"R","tr":""},{"t":"נִּי","a":" ","g":"me","l":"הוּא","s":"2967","m":"Sp1cs","tr":""},{"t":"כִּ֛י","a":" ","g":"(dm)","l":"כִּי","s":"3588","m":"C","tr":"kiy"},{"t":"ט֥וֹב","a":" ","g":"[is].good","l":"טוֹב","s":"2896","m":"Aamsa","tr":"ṭôḇ"},{"t":"מוֹתִ֖","a":"","g":"death","l":"מָוֶת","s":"4194","m":"Ncmsc","tr":""},{"t":"י","a":" ","g":"my","l":"הוּא","s":"2967","m":"Sp1cs","tr":""},{"t":"מֵ","a":"","g":"more","l":"מִן","s":"4480","m":"R","tr":"mē"},{"t":"חַיָּֽ","a":"","g":"than","l":"חַיִּים","s":"2416","m":"Ncmpc","tr":""},{"t":"י","a":"׃ס","g":"my.life","l":"הוּא","s":"2967","m":"Sp1cs","tr":""}],"4:4":[{"t":"וַ","a":"","g":"and","l":"וְ","s":"2050","m":"C","tr":"wa"},{"t":"יֹּ֣אמֶר","a":" ","g":"he.said","l":"אָמַר","s":"559","m":"Vqw3ms","tr":"yyōʾmer"},{"t":"יְהוָ֔ה","a":" ","g":"Yahweh","l":"יהוה","s":"3068","m":"Np","tr":"yəhwāh"},{"t":"הַ","a":"","g":"rightly","l":"הַ","s":"1886","m":"Ti","tr":"ha"},{"t":"הֵיטֵ֖ב","a":" ","g":"(do.well)?","l":"יָטַב","s":"3190","m":"Vha","tr":"hêṭēḇ"},{"t":"חָ֥רָה","a":" ","g":"does.it.burn","l":"חָרָה","s":"2734","m":"Vqp3ms","tr":"ḥārâ"},{"t":"לָֽ","a":"","g":"to","l":"לְ","s":"3807","m":"R","tr":""},{"t":"ךְ","a":"׃","g":"you","l":"הוּא","s":"3509","m":"Sp2fs","tr":""}],"4:5":[{"t":"וַ","a":"","g":"and","l":"וְ","s":"2050","m":"C","tr":"wa"},{"t":"יֵּצֵ֤א","a":" ","g":"he.went.out","l":"יָצָא","s":"3318","m":"Vqw3ms","tr":"yyēṣēʾ"},{"t":"יוֹנָה֙","a":" ","g":"Jonah","l":"יוֹנָה","s":"3124","m":"Np","tr":"yônāh"},{"t":"מִן","a":"־","g":"from","l":"מִן","s":"4480","m":"R","tr":"min-"},{"t":"הָ","a":"","g":"the","l":"הַ","s":"1886","m":"Td","tr":"hā"},{"t":"עִ֔יר","a":" ","g":"city","l":"עִיר","s":"5892","m":"Ncfsa","tr":"ʿiyr"},{"t":"וַ","a":"","g":"and","l":"וְ","s":"2050","m":"C","tr":"wa"},{"t":"יֵּ֖שֶׁב","a":" ","g":"he.sat","l":"יָשַׁב","s":"3427","m":"Vqw3ms","tr":"yyēšeḇ"},{"t":"מִ","a":"","g":"from","l":"מִן","s":"4480","m":"R","tr":"mi"},{"t":"קֶּ֣דֶם","a":" ","g":"east","l":"קֶדֶם","s":"6924","m":"Ncmsa","tr":"qqeḏem"},{"t":"לָ","a":"","g":"of","l":"לְ","s":"3807","m":"Rd","tr":"lā"},{"t":"","a":"","g":"the","l":"הַ","s":"1886","m":"Td","tr":"–"},{"t":"עִ֑יר","a":" ","g":"city","l":"עִיר","s":"5892","m":"Ncfsa","tr":"ʿiyr"},{"t":"וַ","a":"","g":"and","l":"וְ","s":"2050","m":"C","tr":"wa"},{"t":"יַּעַשׂ֩","a":" ","g":"he.made","l":"עָשָׂה","s":"6213","m":"Vqw3ms","tr":"yyaʿaś"},{"t":"ל֨","a":"","g":"for","l":"לְ","s":"3807","m":"R","tr":""},{"t":"וֹ","a":" ","g":"himself","l":"הוּא","s":"2050","m":"Sp3ms","tr":""},{"t":"שָׁ֜ם","a":" ","g":"there","l":"שָׁם","s":"8033","m":"D","tr":"šām"},{"t":"סֻכָּ֗ה","a":" ","g":"a.shelter","l":"סֻכָּה","s":"5521","m":"Ncfsa","tr":"sukkāh"},{"t":"וַ","a":"","g":"and","l":"וְ","s":"2050","m":"C","tr":"wa"},{"t":"יֵּ֤שֶׁב","a":" ","g":"he.sat","l":"יָשַׁב","s":"3427","m":"Vqw3ms","tr":"yyēšeḇ"},{"t":"תַּחְתֶּ֨י","a":"","g":"under","l":"תַּחַת","s":"8478","m":"R","tr":""},{"t":"הָ֙","a":" ","g":"it","l":"הוּא","s":"1886","m":"Sp3fs","tr":""},{"t":"בַּ","a":"","g":"in","l":"בְּ","s":"871","m":"Rd","tr":"ba"},{"t":"","a":"","g":"the","l":"הַ","s":"1886","m":"Td","tr":"–"},{"t":"צֵּ֔ל","a":" ","g":"shade","l":"צֵל","s":"6738","m":"Ncmsa","tr":"ṣṣēl"},{"t":"עַ֚ד","a":" ","g":"until","l":"עַד","s":"5704","m":"R","tr":"ʿaḏ"},{"t":"אֲשֶׁ֣ר","a":" ","g":"that","l":"אֲשֶׁר","s":"834","m":"Tr","tr":"ʾăšer"},{"t":"יִרְאֶ֔ה","a":" ","g":"he.will.see","l":"רָאָה","s":"7200","m":"Vqi3ms","tr":"yirʾeh"},{"t":"מַה","a":"־","g":"what?","l":"מָה","s":"4100","m":"Ti","tr":"mah-"},{"t":"יִּהְיֶ֖ה","a":" ","g":"will.it.be","l":"הָיָה","s":"1961","m":"Vqi3ms","tr":"yyihyeh"},{"t":"בָּ","a":"","g":"in","l":"בְּ","s":"871","m":"Rd","tr":"bā"},{"t":"","a":"","g":"the","l":"הַ","s":"1886","m":"Td","tr":"–"},{"t":"עִֽיר","a":"׃","g":"city","l":"עִיר","s":"5892","m":"Ncfsa","tr":"ʿiyr:"}],"4:6":[{"t":"וַ","a":"","g":"and","l":"וְ","s":"2050","m":"C","tr":"wa"},{"t":"יְמַ֣ן","a":" ","g":"he.appointed","l":"מָנָה","s":"4487","m":"Vpw3ms","tr":"yəman"},{"t":"יְהוָֽה","a":"־","g":"Yahweh","l":"יהוה","s":"3068","m":"Np","tr":"yəhwāh-"},{"t":"אֱ֠לֹהִים","a":" ","g":"God","l":"אֱלֹהִים","s":"430","m":"Ncmpa","tr":"ʾĕlōhîm"},{"t":"קִיקָי֞וֹן","a":" ","g":"a.plant","l":"קִיקָיוֹן","s":"7021","m":"Ncmsa","tr":"qîqāyôn"},{"t":"וַ","a":"","g":"and","l":"וְ","s":"2050","m":"C","tr":"wa"},{"t":"יַּ֣עַל","a":"׀","g":"it.went.up","l":"עָלָה","s":"5927","m":"Vqw3ms","tr":"yyaʿal"},{"t":"מֵ","a":"","g":"(from)","l":"מִן","s":"4480","m":"R","tr":"mē"},{"t":"עַ֣ל","a":" ","g":"over","l":"עַל","s":"5921","m":"R","tr":"ʿal"},{"t":"לְ","a":"","g":"(to)","l":"לְ","s":"3807","m":"R","tr":"lə"},{"t":"יוֹנָ֗ה","a":" ","g":"Jonah","l":"יוֹנָה","s":"3124","m":"Np","tr":"yônāh"},{"t":"לִֽ","a":"","g":"to","l":"לְ","s":"3807","m":"R","tr":"li"},{"t":"הְי֥וֹת","a":" ","g":"be","l":"הָיָה","s":"1961","m":"Vqc","tr":"həyôṯ"},{"t":"צֵל֙","a":" ","g":"shade","l":"צֵל","s":"6738","m":"Ncmsa","tr":"ṣēl"},{"t":"עַל","a":"־","g":"over","l":"עַל","s":"5921","m":"R","tr":"ʿal-"},{"t":"רֹאשׁ֔","a":"","g":"head","l":"רֹאשׁ","s":"7218","m":"Ncmsc","tr":""},{"t":"וֹ","a":" ","g":"his","l":"הוּא","s":"2050","m":"Sp3ms","tr":""},{"t":"לְ","a":"","g":"to","l":"לְ","s":"3807","m":"R","tr":"lə"},{"t":"הַצִּ֥יל","a":" ","g":"deliver","l":"נָצַל","s":"5337","m":"Vhc","tr":"haṣṣiyl"},{"t":"ל֖","a":"","g":"(to)","l":"לְ","s":"3807","m":"R","tr":""},{"t":"וֹ","a":" ","g":"him","l":"הוּא","s":"2050","m":"Sp3ms","tr":""},{"t":"מֵ","a":"","g":"from","l":"מִן","s":"4480","m":"R","tr":"mē"},{"t":"רָֽעָת֑","a":"","g":"distress","l":"רָעָה","s":"7451","m":"Ncfsc","tr":""},{"t":"וֹ","a":" ","g":"his","l":"הוּא","s":"2050","m":"Sp3ms","tr":""},{"t":"וַ","a":"","g":"and","l":"וְ","s":"2050","m":"C","tr":"wa"},{"t":"יִּשְׂמַ֥ח","a":" ","g":"he.rejoiced","l":"שָׂמַח","s":"8055","m":"Vqw3ms","tr":"yyiśmaḥ"},{"t":"יוֹנָ֛ה","a":" ","g":"Jonah","l":"יוֹנָה","s":"3124","m":"Np","tr":"yônāh"},{"t":"עַל","a":"־","g":"on","l":"עַל","s":"5921","m":"R","tr":"ʿal-"},{"t":"הַ","a":"","g":"the","l":"הַ","s":"1886","m":"Td","tr":"ha"},{"t":"קִּֽיקָי֖וֹן","a":" ","g":"plant","l":"קִיקָיוֹן","s":"7021","m":"Ncmsa","tr":"qqîqāyôn"},{"t":"שִׂמְחָ֥ה","a":" ","g":"a.joy","l":"שִׂמְחָה","s":"8057","m":"Ncfsa","tr":"śimḥāh"},{"t":"גְדוֹלָֽה","a":"׃","g":"great","l":"גָּדוֹל","s":"1419","m":"Aafsa","tr":"ḡəḏôlāh:"}],"4:7":[{"t":"וַ","a":"","g":"and","l":"וְ","s":"2050","m":"C","tr":"wa"},{"t":"יְמַ֤ן","a":" ","g":"he.appointed","l":"מָנָה","s":"4487","m":"Vpw3ms","tr":"yəman"},{"t":"הָֽ","a":"","g":"(the)","l":"הַ","s":"1886","m":"Td","tr":"hā"},{"t":"אֱלֹהִים֙","a":" ","g":"God","l":"אֱלֹהִים","s":"430","m":"Ncmpa","tr":"ʾĕlōhîm"},{"t":"תּוֹלַ֔עַת","a":" ","g":"a.worm","l":"תֹּולַעַת","s":"8438","m":"Ncfsa","tr":"tôlaʿaṯ"},{"t":"בַּ","a":"","g":"when","l":"בְּ","s":"871","m":"R","tr":"ba"},{"t":"עֲל֥וֹת","a":" ","g":"came.up","l":"עָלָה","s":"5927","m":"Vqc","tr":"ʿălôṯ"},{"t":"הַ","a":"","g":"the","l":"הַ","s":"1886","m":"Td","tr":"ha"},{"t":"שַּׁ֖חַר","a":" ","g":"dawn","l":"שַׁחַר","s":"7837","m":"Ncmsa","tr":"ššaḥar"},{"t":"לַֽ","a":"","g":"to","l":"לְ","s":"3807","m":"Rd","tr":"la"},{"t":"","a":"","g":"the.next","l":"הַ","s":"1886","m":"Td","tr":"–"},{"t":"מָּחֳרָ֑ת","a":" ","g":"day","l":"מׇחֳרָת","s":"4283","m":"Ncfsa","tr":"mmoḥŏrāṯ"},{"t":"וַ","a":"","g":"and","l":"וְ","s":"2050","m":"C","tr":"wa"},{"t":"תַּ֥ךְ","a":" ","g":"it.attacked","l":"נָכָה","s":"5221","m":"Vhw3fs","tr":"taḵ"},{"t":"אֶת","a":"־","g":"(et)","l":"אֵת","s":"853","m":"To","tr":"ʾeṯ-"},{"t":"הַ","a":"","g":"the","l":"הַ","s":"1886","m":"Td","tr":"ha"},{"t":"קִּֽיקָי֖וֹן","a":" ","g":"plant","l":"קִיקָיוֹן","s":"7021","m":"Ncmsa","tr":"qqiyqāyôn"},{"t":"וַ","a":"","g":"and","l":"וְ","s":"2050","m":"C","tr":"wa"},{"t":"יִּיבָֽשׁ","a":"׃","g":"it.withered","l":"יָבֵשׁ","s":"3001","m":"Vqw3ms","tr":"yyîḇāš:"}],"4:8":[{"t":"וַ","a":"","g":"and","l":"וְ","s":"2050","m":"C","tr":"wa"},{"t":"יְהִ֣י","a":"׀","g":"it.was","l":"הָיָה","s":"1961","m":"Vqw3ms","tr":"yəhiy"},{"t":"כִּ","a":"","g":"just","l":"כְּ","s":"3509","m":"R","tr":"ki"},{"t":"זְרֹ֣חַ","a":" ","g":"as.arose","l":"זָרַח","s":"2224","m":"Vqc","tr":"zərōᵃḥ"},{"t":"הַ","a":"","g":"the","l":"הַ","s":"1886","m":"Td","tr":"ha"},{"t":"שֶּׁ֗מֶשׁ","a":" ","g":"sun","l":"שֶׁמֶשׁ","s":"8121","m":"Ncbsa","tr":"ššemeš"},{"t":"וַ","a":"","g":"and","l":"וְ","s":"2050","m":"C","tr":"wa"},{"t":"יְמַ֨ן","a":" ","g":"he.appointed","l":"מָנָה","s":"4487","m":"Vpw3ms","tr":"yəman"},{"t":"אֱלֹהִ֜ים","a":" ","g":"God","l":"אֱלֹהִים","s":"430","m":"Ncmpa","tr":"ʾĕlōhiym"},{"t":"ר֤וּחַ","a":" ","g":"a.wind","l":"רוּחַ","s":"7307","m":"Ncbsc","tr":"rûᵃḥ"},{"t":"קָדִים֙","a":" ","g":"an.east.wind","l":"קָדִים","s":"6921","m":"Ncmsa","tr":"qāḏîm"},{"t":"חֲרִישִׁ֔ית","a":" ","g":"hot","l":"חֲרִישִׁי","s":"2759","m":"Aafsa","tr":"ḥărîšiyṯ"},{"t":"וַ","a":"","g":"and","l":"וְ","s":"2050","m":"C","tr":"wa"},{"t":"תַּ֥ךְ","a":" ","g":"it.struck","l":"נָכָה","s":"5221","m":"Vhw3ms","tr":"taḵ"},{"t":"הַ","a":"","g":"the","l":"הַ","s":"1886","m":"Td","tr":"ha"},{"t":"שֶּׁ֛מֶשׁ","a":" ","g":"sun","l":"שֶׁמֶשׁ","s":"8121","m":"Ncbsa","tr":"ššemeš"},{"t":"עַל","a":"־","g":"on","l":"עַל","s":"5921","m":"R","tr":"ʿal-"},{"t":"רֹ֥אשׁ","a":" ","g":"the.head","l":"רֹאשׁ","s":"7218","m":"Ncmsc","tr":"rōʾš"},{"t":"יוֹנָ֖ה","a":" ","g":"of.Jonah","l":"יוֹנָה","s":"3124","m":"Np","tr":"yônāh"},{"t":"וַ","a":"","g":"and","l":"וְ","s":"2050","m":"C","tr":"wa"},{"t":"יִּתְעַלָּ֑ף","a":" ","g":"he.became.faint","l":"עָלַף","s":"5968","m":"Vtw3ms","tr":"yyiṯʿallāp̄"},{"t":"וַ","a":"","g":"and","l":"וְ","s":"2050","m":"C","tr":"wa"},{"t":"יִּשְׁאַ֤ל","a":" ","g":"he.asked","l":"שָׁאַל","s":"7592","m":"Vqw3ms","tr":"yyišʾal"},{"t":"אֶת","a":"־","g":"(et)","l":"אֵת","s":"853","m":"To","tr":"ʾeṯ-"},{"t":"נַפְשׁ","a":"","g":"life","l":"נֶפֶשׁ","s":"5315","m":"Ncbsc","tr":""},{"t":"וֹ֙","a":" ","g":"his","l":"הוּא","s":"2050","m":"Sp3ms","tr":""},{"t":"לָ","a":"","g":"to","l":"לְ","s":"3807","m":"R","tr":"lā"},{"t":"מ֔וּת","a":" ","g":"die","l":"מוּת","s":"4191","m":"Vqc","tr":"mûṯ"},{"t":"וַ","a":"","g":"and","l":"וְ","s":"2050","m":"C","tr":"wa"},{"t":"יֹּ֕אמֶר","a":" ","g":"he.said","l":"אָמַר","s":"559","m":"Vqw3ms","tr":"yyōʾmer"},{"t":"ט֥וֹב","a":" ","g":"[is].good","l":"טוֹב","s":"2896","m":"Aamsa","tr":"ṭôḇ"},{"t":"מוֹתִ֖","a":"","g":"death","l":"מוּת","s":"4194","m":"Ncmsc","tr":""},{"t":"י","a":" ","g":"my","l":"הוּא","s":"2967","m":"Sp1cs","tr":""},{"t":"מֵ","a":"","g":"more","l":"מִן","s":"4480","m":"R","tr":"mē"},{"t":"חַיָּֽ","a":"","g":"than","l":"חַיִּים","s":"2416","m":"Ncmpc","tr":""},{"t":"י","a":"׃","g":"my.life","l":"הוּא","s":"2967","m":"Sp1cs","tr":""}],"4:9":[{"t":"וַ","a":"","g":"and","l":"וְ","s":"2050","m":"C","tr":"wa"},{"t":"יֹּ֤אמֶר","a":" ","g":"he.said","l":"אָמַר","s":"559","m":"Vqw3ms","tr":"yyōʾmer"},{"t":"אֱלֹהִים֙","a":" ","g":"God","l":"אֱלֹהִים","s":"430","m":"Ncmpa","tr":"ʾĕlōhîm"},{"t":"אֶל","a":"־","g":"to","l":"אֶל","s":"413","m":"R","tr":"ʾel-"},{"t":"יוֹנָ֔ה","a":" ","g":"Jonah","l":"יוֹנָה","s":"3124","m":"Np","tr":"yônāh"},{"t":"הַ","a":"","g":"rightly","l":"הַ","s":"1886","m":"Ti","tr":"ha"},{"t":"הֵיטֵ֥ב","a":" ","g":"(do.well)?","l":"יָטַב","s":"3190","m":"Vha","tr":"hêṭēḇ"},{"t":"חָרָֽה","a":"־","g":"does.it.burn","l":"חָרָה","s":"2734","m":"Vqp3ms","tr":"ḥārāh-"},{"t":"לְ","a":"","g":"to","l":"לְ","s":"3807","m":"R","tr":""},{"t":"ךָ֖","a":" ","g":"you","l":"הוּא","s":"3509","m":"Sp2ms","tr":""},{"t":"עַל","a":"־","g":"on","l":"עַל","s":"5921","m":"R","tr":"ʿal-"},{"t":"הַ","a":"","g":"the","l":"הַ","s":"1886","m":"Td","tr":"ha"},{"t":"קִּֽיקָי֑וֹן","a":" ","g":"plant","l":"קִיקָיוֹן","s":"7021","m":"Ncmsa","tr":"qqiyqāyôn"},{"t":"וַ","a":"","g":"and","l":"וְ","s":"2050","m":"C","tr":"wa"},{"t":"יֹּ֕אמֶר","a":" ","g":"he.said","l":"אָמַר","s":"559","m":"Vqw3ms","tr":"yyōʾmer"},{"t":"הֵיטֵ֥ב","a":" ","g":"rightly.(do.well)","l":"יָטַב","s":"3190","m":"Vha","tr":"hêṭēḇ"},{"t":"חָֽרָה","a":"־","g":"it.burns","l":"חָרָה","s":"2734","m":"Vqp3ms","tr":"ḥārâ-"},{"t":"לִ֖","a":"","g":"to","l":"לְ","s":"3807","m":"R","tr":""},{"t":"י","a":" ","g":"me","l":"הוּא","s":"2967","m":"Sp1cs","tr":""},{"t":"עַד","a":"־","g":"to","l":"עַד","s":"5704","m":"R","tr":"ʿaḏ-"},{"t":"מָֽוֶת","a":"׃","g":"death","l":"מָוֶת","s":"4194","m":"Ncmsa","tr":"māweṯ:"}],"4:10":[{"t":"וַ","a":"","g":"and","l":"וְ","s":"2050","m":"C","tr":"wa"},{"t":"יֹּ֣אמֶר","a":" ","g":"he.said","l":"אָמַר","s":"559","m":"Vqw3ms","tr":"yyōʾmer"},{"t":"יְהוָ֔ה","a":" ","g":"Yahweh","l":"יהוה","s":"3068","m":"Np","tr":"yəhwāh"},{"t":"אַתָּ֥ה","a":" ","g":"you","l":"אַתָּה","s":"859","m":"Pp2ms","tr":"ʾattāh"},{"t":"חַ֨סְתָּ֙","a":" ","g":"you.had.compassion","l":"חוּס","s":"2347","m":"Vqp2ms","tr":"ḥasətā"},{"t":"עַל","a":"־","g":"on","l":"עַל","s":"5921","m":"R","tr":"ʿal-"},{"t":"הַ","a":"","g":"the","l":"הַ","s":"1886","m":"Td","tr":"ha"},{"t":"קִּ֣יקָי֔וֹן","a":" ","g":"plant","l":"קִיקָיוֹן","s":"7021","m":"Ncmsa","tr":"qqiyqāyôn"},{"t":"אֲשֶׁ֛ר","a":" ","g":"which","l":"אֲשֶׁר","s":"834","m":"Tr","tr":"ʾăšer"},{"t":"לֹא","a":"־","g":"not","l":"לֹא","s":"3808","m":"Tn","tr":"lōʾ-"},{"t":"עָמַ֥לְתָּ","a":" ","g":"you.had.toiled","l":"עָמַל","s":"5998","m":"Vqp2ms","tr":"ʿāmalətā"},{"t":"בּ֖","a":"","g":"in","l":"בְּ","s":"871","m":"R","tr":""},{"t":"וֹ","a":" ","g":"it","l":"הוּא","s":"2050","m":"Sp3ms","tr":""},{"t":"וְ","a":"","g":"and","l":"וְ","s":"2050","m":"C","tr":"wə"},{"t":"לֹ֣א","a":" ","g":"not","l":"לֹא","s":"3808","m":"Tn","tr":"lōʾ"},{"t":"גִדַּלְתּ֑","a":"","g":"you","l":"גָּדַל","s":"1431","m":"Vpp2ms","tr":""},{"t":"וֹ","a":" ","g":"had.made.it.grow","l":"הוּא","s":"2050","m":"Sp3ms","tr":""},{"t":"שֶׁ","a":"","g":"which","l":"שֶׁ","s":"7578","m":"Tr","tr":"še"},{"t":"בִּן","a":"־","g":"a.son","l":"בֵּן","s":"1121","m":"Ncmsc","tr":"bin-"},{"t":"לַ֥יְלָה","a":" ","g":"of.a.night","l":"לַיְלָה","s":"3915","m":"Ncmsa","tr":"layəlâ"},{"t":"הָיָ֖ה","a":" ","g":"it.was","l":"הָיָה","s":"1961","m":"Vqp3ms","tr":"hāyāh"},{"t":"וּ","a":"","g":"and","l":"וְ","s":"2050","m":"C","tr":"û"},{"t":"בִן","a":"־","g":"a.son","l":"בֵּן","s":"1121","m":"Ncmsc","tr":"ḇin-"},{"t":"לַ֥יְלָה","a":" ","g":"of.a.night","l":"לַיְלָה","s":"3915","m":"Ncmsa","tr":"layəlâ"},{"t":"אָבָֽד","a":"׃","g":"it.perished","l":"אָבַד","s":"6","m":"Vqp3ms","tr":"ʾāḇāḏ:"}],"4:11":[{"t":"וַֽ","a":"","g":"and","l":"וְ","s":"2050","m":"C","tr":"wa"},{"t":"אֲנִי֙","a":" ","g":"I","l":"אֲנִי","s":"589","m":"Pp1cs","tr":"ʾănî"},{"t":"לֹ֣א","a":" ","g":"not","l":"לֹא","s":"3808","m":"Tn","tr":"lōʾ"},{"t":"אָח֔וּס","a":" ","g":"will.I.have.compassion?","l":"חוּס","s":"2347","m":"Vqi1cs","tr":"ʾāḥûs"},{"t":"עַל","a":"־","g":"on","l":"עַל","s":"5921","m":"R","tr":"ʿal-"},{"t":"נִינְוֵ֖ה","a":" ","g":"Nineveh","l":"נִינְוֵה","s":"5210","m":"Np","tr":"nînəwēh"},{"t":"הָ","a":"","g":"the","l":"הַ","s":"1886","m":"Td","tr":"hā"},{"t":"עִ֣יר","a":" ","g":"city","l":"עִיר","s":"5892","m":"Ncfsa","tr":"ʿiyr"},{"t":"הַ","a":"","g":"(the)","l":"הַ","s":"1886","m":"Td","tr":"ha"},{"t":"גְּדוֹלָ֑ה","a":" ","g":"great","l":"גָּדוֹל","s":"1419","m":"Aafsa","tr":"gəḏôlāh"},{"t":"אֲשֶׁ֣ר","a":" ","g":"which","l":"אֲשֶׁר","s":"834","m":"Tr","tr":"ʾăšer"},{"t":"יֶשׁ","a":"־","g":"there.[are]","l":"יֵשׁ","s":"3426","m":"Tm","tr":"yeš-"},{"t":"בָּ֡","a":"","g":"in","l":"בְּ","s":"871","m":"R","tr":""},{"t":"הּ","a":" ","g":"it","l":"הוּא","s":"1886","m":"Sp3fs","tr":""},{"t":"הַרְבֵּה֩","a":" ","g":"many","l":"רָבָה","s":"7235","m":"Vha","tr":"harbēh"},{"t":"מִֽ","a":"","g":"more","l":"מִן","s":"4480","m":"R","tr":"mi"},{"t":"שְׁתֵּים","a":"־","g":"than.two.plus","l":"שְׁנַיִם","s":"8147","m":"Acfda","tr":"šətêm-"},{"t":"עֶשְׂרֵ֨ה","a":" ","g":"ten","l":"עֶשְׂרֵה","s":"6240","m":"Acfsa","tr":"ʿeśrēh"},{"t":"רִבּ֜וֹ","a":" ","g":"ten.thousand","l":"רִבֹּוא","s":"7239","m":"Acbsa","tr":"ribô"},{"t":"אָדָ֗ם","a":" ","g":"person[s]","l":"אָדָם","s":"120","m":"Ncmsa","tr":"ʾāḏām"},{"t":"אֲשֶׁ֤ר","a":" ","g":"who","l":"אֲשֶׁר","s":"834","m":"Tr","tr":"ʾăšer"},{"t":"לֹֽא","a":"־","g":"not","l":"לֹא","s":"3808","m":"Tn","tr":"lōʾ-"},{"t":"יָדַע֙","a":" ","g":"he.distinguishes","l":"יָדַע","s":"3045","m":"Vqp3ms","tr":"yāḏaʿ"},{"t":"בֵּין","a":"־","g":"between","l":"בֵּין","s":"996","m":"R","tr":"bên-"},{"t":"יְמִינ֣","a":"","g":"hand","l":"יָמִין","s":"3225","m":"Ncfsc","tr":""},{"t":"וֹ","a":" ","g":"his.right","l":"הוּא","s":"2050","m":"Sp3ms","tr":""},{"t":"לִ","a":"","g":"and","l":"לְ","s":"3807","m":"R","tr":"li"},{"t":"שְׂמֹאל֔","a":"","g":"left","l":"שְׂמֹאל","s":"8040","m":"Ncmsc","tr":""},{"t":"וֹ","a":" ","g":"his","l":"הוּא","s":"2050","m":"Sp3ms","tr":""},{"t":"וּ","a":"","g":"and","l":"וְ","s":"2050","m":"R","tr":"û"},{"t":"בְהֵמָ֖ה","a":" ","g":"livestock","l":"בְּהֵמָה","s":"929","m":"Ncfsa","tr":"ḇəhēmāh"},{"t":"רַבָּֽה","a":"׃","g":"much","l":"רַב","s":"7227","m":"Aafsa","tr":"rabbāh:"}]}}